Workbook

Sheet Balance Sheet
A1: Column1 | B1: Column2 | C1: Column3 | D1: Column4 | E1: Column5 | F1: Column6 | G1: Column7 | H1: Column8
A2: Mã số | B2: Chỉ tiêu | D2: 2022 | E2: 2023 | F2: 2024
A3: 100 | B3: TÀI SẢN NGẮN HẠN (current assets) | C3: Current Assets | D3: 12258434228464 | E3: 13186804684705 | F3: 15547886617815
A4: 110 | B4: Tiền và các khoản tương đương tiền | C4: Cash and Cash Equivalents | D4: 242815476591 | E4: 501386999566 | F4: 427778817941
A5: 111 | B5: Tiền | C5: Cash | D5: 242065476591 | E5: 500636999566 | F5: 426922790174
A6: 112 | B6: Các khoản tương đương tiền | C6: Cash Equivalents | D6: 750000000 | E6: 750000000 | F6: 856027767
A7: 120 | B7: Đầu tư tài chính ngắn hạn | C7: Short-term Financial Investments | D7: 5000000000 | E7: 20560958904 | F7: 21278737672
A8: 123 | B8: Đầu tư nắm giữ đến ngày đáo hạn | C8: Held-to-Maturity Investments | D8: 5000000000 | E8: 20560958904 | F8: 21278737672
A9: 130 | B9: Các khoản phải thu ngắn hạn | C9: Short-term Accounts Receivables | D9: 8315127736295 | E9: 8405245948063 | F9: 10613408098640
A10: 131 | B10: Phải thu ngắn hạn của khách hàng | C10: Accounts Receivable from Customer | D10: 7934070297881 | E10: 7416195465814 | F10: 9337308709135
A11: 132 | B11: Trả trước cho người bán ngắn hạn | C11: Advances to Suppliers | D11: 95559044734 | E11: 26549614993 | F11: 535694209756
A12: 135 | B12: Phải thu về cho vay ngắn hạn | C12: Short-term Loans Receivable | D12: - | E12: 118500000000 | F12: 374000000000
A13: 136 | B13: Phải thu ngắn hạn khác | C13: Other Short-term Receivables | D13: 299205562269 | E13: 854774675210 | F13: 366833818035
A14: 137 | B14: Dự phòng phải thu ngắn hạn khó đòi | C14: Allowance for Doubtful Receivables | D14: -13707168589 | E14: -10773807954 | F14: -428638286
A15: 140 | B15: Hàng tồn kho | C15: Inventories | D15: 3185372278891 | E15: 3749491109277 | F15: 3943145442782
A16: 141 | B16: Hàng tồn kho | C16: Inventory | D16: 3377955693089 | E16: 3876500070101 | F16: 4064994260176
A17: 149 | B17: Dự phòng giảm giá hàng tồn kho | C17: Allowance for Inventory Write-down | D17: -192583414198 | E17: -127008960824 | F17: -121848817394
A18: 150 | B18: Tài sản ngắn hạn khác | C18: Other Current Assets | D18: 510118736687 | E18: 510119668895 | F18: 542275520780
A19: 151 | B19: Chi phí trả trước ngắn hạn | C19: Short-term Prepaid Expenses | D19: 94748267020 | E19: 96483062965 | F19: 86974686528
A20: 152 | B20: Thuế GTGT được khấu trừ | C20: Deductible VAT | D20: 286790842330 | E20: 285106020138 | F20: 326902155004
A21: 153 | B21: Thuế và các khoản khác phải thu Nhà nước | C21: Taxes and Other Receivables from the State | D21: 128579627337 | E21: 128530585792 | F21: 128398679248
A22: 200 | B22: TÀI SẢN DÀI HẠN (non-current assets) | C22: Non-current Assets | D22: 5118727087531 | E22: 4924991584484 | F22: 4763897298254
A23: 210 | B23: Các khoản phải thu dài hạn | C23: Long-term Receivables | D23: 241195291600 | E23: 140931524246 | F23: 175741186200
A24: 215 | B24: Phải thu về cho vay dài hạn | C24: Long-term Loans Receivable | D24: 70700000000 | E24: - | F24: -
A25: 216 | B25: Phải thu dài hạn khác | C25: Other Long-term Receivables | D25: 170495291600 | E25: 140931524246 | F25: 175741186200
A26: 220 | B26: Tài sản cố định | C26: Fixed Asset | D26: 1198450061079 | E26: 1016313002019 | F26: 844402354164
A27: 221 | B27: TSCĐ hữu hình | C27: Property, Plant and Equipment | D27: 1014508752822 | E27: 848743235444 | F27: 666709132303
A28: 222 | B28: Nguyên giá | C28: Historical Cost | D28: 3794307134043 | E28: 3888602489525 | F28: 3851460375484
A29: 223 | B29: Giá trị hao mòn lũy kế | C29: Accumulated Depreciation | D29: -2779798381221 | E29: -3039859254081 | F29: -3184751243181
A30: 227 | B30: TSCĐ vô hình | C30: Intangible Assets | D30: 183941308257 | E30: 167569766575 | F30: 177693221861
A31: 228 | B31: Nguyên giá | C31: Historical Cost | D31: 259431861261 | E31: 254559214510 | F31: 270506314710
A32: 229 | B32: Giá trị hao mòn lũy kế | C32: Accumulated Amortization | D32: -75490553004 | E32: -86989447935 | F32: -92813092849
A33: 240 | B33: Tài sản dở dang dài hạn | C33: Long-term Work in Progress | D33: 106037865309 | E33: 27180502737 | F33: 9027013569
A34: 242 | B34: Chi phí xây dựng cơ bản dở dang | C34: Construction in Progress (CIP) | D34: 106037865309 | E34: 27180502737 | F34: 9027013569
A35: 250 | B35: Đầu tư tài chính dài hạn | C35: Long-term Financial Investments | D35: 3393850000000 | E35: 3589850000000 | F35: 3595595087671
A36: 251 | B36: Đầu tư vào công ty con | C36: Investments in Subsidiaries | D36: 3377850000000 | E36: 3588850000000 | F36: 3594595087671
A37: 252 | B37: Đầu tư vào công ty liên kết | C37: Investments in Associates | D37: - | E37: - | F37: -
A38: 255 | B38: Đầu tư nắm giữ đến ngày đáo hạn | C38: Held-to-Maturity Investments | D38: 16000000000 | E38: 1000000000 | F38: 1000000000
A39: 260 | B39: Tài sản dài hạn khác | C39: Other Non-current Assets | D39: 179193869543 | E39: 150716555482 | F39: 139131656650
A40: 261 | B40: Chi phí trả trước dài hạn | C40: Long-term Prepaid Expenses | D40: 69639780740 | E40: 100428317304 | F40: 62373737291
A41: 262 | B41: Tài sản thuế thu nhập hoãn lại | C41: Deferred Tax Assets | D41: 109554088803 | E41: 50288238178 | F41: 76757919359
A42: 270 | B42: TỔNG TÀI SẢN | C42: Total Assets | D42: 17377161315995 | E42: 18111796269189 | F42: 20311783916069
A43: 300 | B43: NỢ PHẢI TRẢ | C43: Liabilities | D43: 6210033388769 | E43: 6829845298714 | F43: 8878813931686
A44: 310 | B44: Nợ ngắn hạn | C44: Current Liabilities | D44: 6195799689582 | E44: 6815609482547 | F44: 8864853420561
A45: 311 | B45: Phải trả người bán ngắn hạn | C45: Accounts Payable | D45: 1970635586928 | E45: 3330483232614 | F45: 2853606214481
A46: 312 | B46: Người mua trả tiền trước ngắn hạn | C46: Advances from Customers | D46: 176845202295 | E46: 129957335766 | F46: 179998887975
A47: 313 | B47: Thuế và các khoản phải nộp Nhà nước | C47: Taxes and Other Payables to the State Budget | D47: 5275868275 | E47: 145505586644 | F47: 74417109924
A48: 314 | B48: Phải trả người lao động | C48: Employee Payables | D48: 64245590725 | E48: 48600453107 | F48: 64468071697
A49: 315 | B49: Chi phí phải trả ngắn hạn | C49: Accrued Expenses | D49: 207561319455 | E49: 66684028030 | F49: 208807717032
... A58: 411 | B58: Vốn góp của chủ sở hữu | C58: Contributed Capital | D58: 5980549860000 | E58: 6159823090000 | F58: 6159823090000
A59: 411a | B59: Cổ phiếu phổ thông có quyền biểu quyết | C59: Ordinary Shares | D59: 5980549860000 | E59: 6159823090000 | F59: 6159823090000
A60: 412 | B60: Thặng dư vốn cổ phần | C60: Share Premium | D60: 157292539068 | E60: 157292539068 | F60: 157292539068
A61: 420 | B61: Quỹ khác thuộc vốn chủ sở hữu | C61: Other Equity Funds | D61: 187499009876 | E61: 77910496944 | F61: 50993213769
A62: 421 | B62: Lợi nhuận sau thuế chưa phân phối | C62: Retained Earnings | D62: 4841786518282 | E62: 4886924844463 | F62: 5064861141546
A63: 421a | B63: LN chưa phân phối lũy kế năm trước | C63: Retained Earnings Brought Forward | D63: 4793615960838 | E63: 4638635861919 | F63: 4576082907573
A64: 421b | B64: LN chưa phân phối năm nay | C64: Current Year Retained Earnings | D64: 48170557444 | E64: 248288982544 | F64: 488778233973
A65: 440 | B65: TỔNG NGUỒN VỐN | C65: Total Liabilities and Equity | D65: 17377161315995 | E65: 18111796269189 | F65: 20311783916069

Sheet Income Statement
A1: Mã số | B1: Chỉ tiêu | C1: Eng | D1: Thuyết minh | E1: 2022 | F1: 2023 | G1: 2024
A2: 1 | B2: Doanh thu bán hàng và cung cấp dịch vụ | C2: Revenue from sales and service provision | D2: 27 | E2: 81450228213277 | F2: 52881019564133 | G2: 67051370845971
A3: 2 | B3: Các khoản giảm trừ doanh thu | C3: Sales deductions | D3: 27 | E3: 260746998178 | F3: 276256396943 | G3: 338823047220
A5: 10 | B5: Doanh thu thuần về bán hàng và cung cấp dịch vụ | C5: Net revenue from sales and service provision | D5: 27 | E5: 81189481215099 | F5: 52604763167190 | G5: 66712547798751
A6: 11 | B6: Giá vốn hàng bán và dịch vụ cung cấp | C6: Cost of goods sold and services provided | D6: 28 | E6: 77388423409761 | F6: 50476627454498 | G6: 63473799048283
A7: 20 | B7: Lợi nhuận gộp (20 = 10 - 11) | C7: Gross profit (20 = 10 - 11) | E7: 3801057805338 | F7: 2128135712692 | G7: 3238748750468
A8: 21 | B8: Doanh thu hoạt động tài chính | C8: Financial income | D8: 29 | E8: 425167604879 | F8: 800850256543 | G8: 652938094707
A9: 22 | B9: Chi phí tài chính | C9: Financial expenses | D9: 30 | E9: 419889233636 | F9: 300217604297 | G9: 251550025718
A10: 25 | B10: Chi phí bán hàng | C10: Selling expenses | D10: 31 | E10: 3469159524662 | F10: 2121829595199 | G10: 2858708812560
A11: 26 | B11: Chi phí quản lý doanh nghiệp | C11: General and administrative expenses | D11: 32 | E11: 323017357209 | F11: 242553285595 | G11: 308367699972
A12: 30 | B12: Lợi nhuận thuần từ hoạt động kinh doanh | C12: Operating profit | E12: 14159294710 | F12: 264385484144 | G12: 473060306925
A14: 31 | B14: Thu nhập khác | C14: Other income | E14: 37281371157 | F14: 45338320487 | G14: 34684261898
A15: 32 | B15: Chi phí khác | C15: Other expenses | E15: 2028544004 | F15: 631991708 | G15: 5192249642
A16: 40 | B16: Lợi nhuận/(lỗ) khác (40 = 31 - 32) | C16: Other profit/(loss) (40 = 31 - 32) | E16: 35252827153 | F16: 44706328779 | G16: 29492012256
A17: 50 | B17: Tổng lợi nhuận kế toán trước thuế (50 = 30 + 40) | C17: Total accounting profit before tax (50 = 30 + 40) | E17: 49412121863 | F17: 309091812923 | G17: 502552319181
A18: 51 | B18: Chi phí thuế TNDN hiện hành | C18: Current corporate income tax expense | D18: 34 | E18: 23681645484 | F18: 1536979754 | G18: 99693200
A19: 52 | B19: Lợi ích thuế TNDN hoãn lại | C19: Deferred corporate income tax benefit | D19: 34 | E19: -22440081065 | F19: 59265850625 | G19: 26469681181
A20: 60 | B20: Lợi nhuận thuần sau thuế TNDN (60 = 50 - 51 - 52) | C20: Net profit after corporate income tax (60 = 50 - 51 - 52) | E20: 48170557444 | F20: 248288982544 | G20: 528922307162

Sheet Cash flow Statement
A1: Chỉ tiêu | C1: 2022 (VND) | D1: 2023 (VND) | E1: 2024 (VND)
A2: LƯU CHUYỂN TIỀN TỪ HOẠT ĐỘNG KINH DOANH | B2: CASH FLOWS FROM OPERATING ACTIVITIES
A3: Lợi nhuận kế toán trước thuế | B3: Profit before Tax | C3: 49412121863 | D3: 309091812923 | E3: 502552319181
A4: Khấu hao tài sản cố định | B4: Depreciation of Fixed Assets | C4: 288742037855 | D4: 296698963838 | E4: 213396307446
A5: Các khoản hoàn nhập dự phòng | B5: Reversal of Provisions | C5: 112682357532 | D5: -54798528440 | E5: -5435448472
A6: Lỗ/(lãi) chênh lệch tỷ giá hối đoái | B6: Foreign Exchange Loss/(Gain) | C6: -5999777701 | D6: -2114003286 | E6: 4859887308
A7: Lãi từ hoạt động đầu tư | B7: Investment Income | C7: -182386015343 | D7: -582268394623 | E7: -325217103728
A8: Chi phí lãi vay | B8: Interest Expense | C8: 176518452634 | D8: 184694883045 | E8: 131805003372
A9: Lợi nhuận từ HĐKD trước thay đổi vốn lưu động | B9: Operating Profit before Changes in Working Capital | C9: 438969176840 | D9: 151304733457 | E9: 521960965107
A11: (Tăng)/giảm các khoản phải thu | B11: (Increase)/Decrease in Receivables | C11: 1825657571725 | D11: 455788862582 | E11: -1800373698676
A12: Tăng hàng tồn kho | B12: Increase in Inventories | C12: 3086823027253 | D12: -508889546680 | E12: -188494190075
A13: Tăng các khoản phải trả | B13: Increase in Payables | C13: -3677954974368 | D13: 1544513703402 | E13: 274588619440
A14: Giảm chi phí trả trước | B14: Decrease in Prepaid Expenses | C14: -13914683956 | D14: 23096871939 | E14: 55298002073
A15: Tiền lãi vay đã trả | B15: Interest Paid | C15: -182460644247 | D15: -186167929380 | E15: -131111426969
A16: Thuế TNDN đã nộp | B16: Corporate Income Tax Paid | C16: -288320745818 | D16: -1461479656 | E16: –
A17: Tiền chi khác từ hoạt động kinh doanh | B17: Other Cash Payments for Operating Activities | C17: -117030852331 | D17: -191696191456 | E17: -182993643610
A18: Lưu chuyển tiền thuần từ HĐKD | B18: Net Cash Flows from Operating Activities | C18: 1071767875098 | D18: 1286489024208 | E18: -1451125372710
A20: LƯU CHUYỂN TIỀN TỪ HOẠT ĐỘNG ĐẦU TƯ | B20: CASH FLOWS FROM INVESTING ACTIVITIES
A21: Tiền chi mua sắm TSCĐ và tài sản dài hạn | B21: Payments for Acquisition of Fixed Assets and Long-term Assets | C21: -328785899096 | D21: -178762599745 | E21: -560646561404
A22: Tiền thu từ thanh lý TSCĐ | B22: Proceeds from Disposal of Fixed Assets | C22: 24389427659 | D22: 33972301805 | E22: 36807283700
A23: Tiền chi cho vay và tiền gửi ngân hàng >3 tháng | B23: Payments for Loans Granted and Bank Deposits over 3 Months | C23: -2700000000 | D23: -136060958904 | E23: -288417778768
A24: Tiền thu hồi cho vay và tiền gửi >3 tháng | B24: Collections from Loans Granted and Bank Deposits over 3 Months | C24: – | D24: 15000000000 | E24: 28000000000
A25: Tiền chi đầu tư vào công ty con | B25: Payments for Investments in Subsidiaries | C25: – | D25: -130845602739 | E25: -1500000000
A26: Tiền thu lãi tiền gửi, cổ tức | B26: Interest and Dividend Received | C26: 231166167254 | D26: 9167953933 | E26: 40168882612
A27: Lưu chuyển tiền thuần từ HĐĐT | B27: Net Cash Flows from Investing Activities | C27: -75930304183 | D27: -387528905650 | E27: -745588173860
A29: LƯU CHUYỂN TIỀN TỪ HOẠT ĐỘNG TÀI CHÍNH | B29: CASH FLOWS FROM FINANCING ACTIVITIES
A30: Tiền thu từ phát hành cổ phiếu | B30: Proceeds from Issuance of Shares | C30: – | D30: – | E30: 22110000000
A31: Tiền thu từ đi vay | B31: Proceeds from Borrowings | C31: – | D31: 21420117233606 | E31: 31261321526957
A32: Tiền chi trả nợ gốc vay | B32: Repayment of Borrowings/Annual principal payment obligation | C32: -33679445401829 | D32: -22061887581884 | E32: -28854393170251
A33: Tiền chi trả cổ tức | B33: Dividend Payments | C33: – | D33: -5531000 | E33: -307574177800
A34: Lưu chuyển tiền thuần từ HĐTC | B34: Net Cash Flows from Financing Activities | C34: – | D34: -641775879278 | E34: 2121464178906
A36: Lưu chuyển tiền thuần trong năm | B36: Net Increase/(Decrease) in Cash and Cash Equivalents | C36: 995837570915 | D36: 257184239280 | E36: -75249367664
A37: Tiền và tương đương tiền đầu năm | B37: Cash and Cash Equivalents at the Beginning of the Year | C37: 242815476591 | D37: 501386999566 | E37: 427778817941
A38: Ảnh hưởng thay đổi tỷ giá | B38: Effect of Exchange Rate Changes | C38: – | D38: 1387283695 | E38: 1641186039
A39: Tiền và tương đương tiền cuối năm | B39: Cash and Cash Equivalents at the End of the Year | C39: 501386999566 | D39: 501386999566 | E39: 427778817941

Sheet 2. Financial statement
A1: Total asset trend
A2: Year | B2: Total Assets (trillion VND) | C2: Asset growth (%) | D2: Total Liabilities and Equity (trillion VND)
A3: 2022 | B3: ='Balance Sheet'!D42/1000000000000 -> 17.377161 | D3: ='Balance Sheet'!D65/1000000000000 -> 17.377161
A4: 2023 | B4: ='Balance Sheet'!E42/1000000000000 -> 18.111796 | C4: =(B4-B3)/B3 -> 0.04227589 | D4: ='Balance Sheet'!E65/1000000000000 -> 18.111796
A5: 2024 | B5: ='Balance Sheet'!F42/1000000000000 -> 20.311784 | C5: =(B5-B4)/B4 -> 0.12146712 | D5: ='Balance Sheet'!F65/1000000000000 -> 20.311784
A7: Structure of Total assets
A8: Year | B8: 2022 | C8: 2023 | D8: 2024
A9: CA(%) | B9: ='Balance Sheet'!D3/'Balance Sheet'!D42 -> 0.70543364 | C9: ='Balance Sheet'!E3/'Balance Sheet'!E42 -> 0.72807824 | D9: ='Balance Sheet'!F3/'Balance Sheet'!F42 -> 0.7654614
A10: NCA(%) | B10: ='Balance Sheet'!D22/'Balance Sheet'!D42 -> 0.29456636 | C10: ='Balance Sheet'!E22/'Balance Sheet'!E42 -> 0.27192176 | D10: ='Balance Sheet'!F22/'Balance Sheet'!F42 -> 0.2345386
A12: CA structure
B13: 2022 | C13: 2023 | D13: 2024 | E13: 2022 | F13: 2023 | G13: 2024
A14: Current Assets | B14: 12258434228464 | C14: 13186804684705 | D14: 15547886617815
A15: Cash and Cash Equivalents | B15: 242815476591 | C15: 501386999566 | D15: 427778817941 | E15: =B15/B14 -> 0.019808034 | F15: =C15/C14 -> 0.038021872 | G15: =D15/D14 -> 0.027513631
A16: Cash | B16: 242065476591 | C16: 500636999566 | D16: 426922790174
A17: Cash Equivalents | B17: 750000000 | C17: 750000000 | D17: 856027767
A18: Short-term Financial Investments | B18: 5000000000 | C18: 20560958904 | D18: 21278737672 | E18: =B18/B14 -> 0.00040788243 | F18: =C18/C14 -> 0.0015592071 | G18: =D18/D14 -> 0.0013685936
A19: Held-to-Maturity Investments | B19: 5000000000 | C19: 20560958904 | D19: 21278737672
A20: Short-term Receivables | B20: 8315127736295 | C20: 8405245948063 | D20: 10613408098640 | E20: =B20/B14 -> 0.67831891 | F20: =C20/C14 -> 0.63739823 | G20: =D20/D14 -> 0.68262706
A21: Accounts Receivable | B21: 7934070297881 | C21: 7416195465814 | D21: 9337308709135
A22: Advances to Suppliers | B22: 95559044734 | C22: 26549614993 | D22: 535694209756
A23: Short-term Loans Receivable | B23: - | C23: 118500000000 | D23: 374000000000
A24: Other Short-term Receivables | B24: 299205562269 | C24: 854774675210 | D24: 366833818035
A25: Allowance for Doubtful Receivables | B25: -13707168589 | C25: -10773807954 | D25: -428638286
A26: Inventories | B26: 3185372278891 | C26: 3749491109277 | D26: 3943145442782 | E26: =B26/B14 -> 0.25985148 | F26: =C26/C14 -> 0.28433659 | G26: =D26/D14 -> 0.25361295
A27: Inventory | B27: 3377955693089 | C27: 3876500070101 | D27: 4064994260176
A28: Allowance for Inventory Write-down | B28: -192583414198 | C28: -127008960824 | D28: -121848817394
A29: Other Current Assets | B29: 510118736687 | C29: 510119668895 | D29: 542275520780 | E29: =B29/B14 -> 0.041613694 | F29: =C29/C14 -> 0.0386841 | G29: =D29/D14 -> 0.034877764
A30: Short-term Prepaid Expenses | B30: 94748267020 | C30: 96483062965 | D30: 86974686528
A31: Deductible VAT | B31: 286790842330 | C31: 285106020138 | D31: 326902155004
A32: Taxes and Other Receivables from the State | B32: 128579627337 | C32: 128530585792 | D32: 128398679248
A34: NCA structure
B35: 2022 | C35: 2023 | D35: 2024 | E35: 2022 | F35: 2023 | G35: 2024
A36: Non-current Assets | B36: 5118727087531 | C36: 4924991584484 | D36: 4763897298254
A37: Long-term Receivables | B37: 241195291600 | C37: 140931524246 | D37: 175741186200
A38: Long-term Loans Receivable | B38: 70700000000 | C38: - | D38: -
A39: Other Long-term Receivables | B39: 170495291600 | C39: 140931524246 | D39: 175741186200
A40: Fixed Asset | B40: 1198450061079 | C40: 1016313002019 | D40: 844402354164 | E40: =B40/B36 -> 0.23413049 | F40: =C40/C36 -> 0.20635832 | G40: =D40/D36 -> 0.17725033
A41: Property, Plant and Equipment | B41: 1014508752822 | C41: 848743235444 | D41: 666709132303
A42: Historical Cost | B42: 3794307134043 | C42: 3888602489525 | D42: 3851460375484
A43: Accumulated Depreciation | B43: -2779798381221 | C43: -3039859254081 | D43: -3184751243181
A44: Intangible Assets | B44: 183941308257 | C44: 167569766575 | D44: 177693221861
A45: Historical Cost | B45: 259431861261 | C45: 254559214510 | D45: 270506314710
A46: Accumulated Amortization | B46: -75490553004 | C46: -86989447935 | D46: -92813092849
A47: Long-term Work in Progress | B47: 106037865309 | C47: 27180502737 | D47: 9027013569 | E47: =B47/B36 -> 0.020715671 | F47: =C47/C36 -> 0.0055188932 | G47: =D47/D36 -> 0.00189488
A48: Construction in Progress (CIP) | B48: 106037865309 | C48: 27180502737 | D48: 9027013569
A49: Long-term Financial Investments | B49: 3393850000000 | C49: 3589850000000 | D49: 3595595087671 | E49: =B49/B36 -> 0.66302617 | F49: =C49/C36 -> 0.7289048 | G49: =D49/D36 -> 0.75475915
A50: Investments in Subsidiaries | B50: 3377850000000 | C50: 3588850000000 | D50: 3594595087671
A51: Investments in Associates | B51: - | C51: - | D51: -
A52: Held-to-Maturity Investments | B52: 16000000000 | C52: 1000000000 | D52: 1000000000
A53: Other Non-current Assets | B53: 179193869543 | C53: 150716555482 | D53: 139131656650 | E53: =B53/B36 -> 0.035007506 | F53: =C53/C36 -> 0.030602399 | G53: =D53/D36 -> 0.029205427
A54: Long-term Prepaid Expenses | B54: 69639780740 | C54: 100428317304 | D54: 62373737291
A55: Deferred Tax Assets | B55: 109554088803 | C55: 50288238178 | D55: 76757919359
A57: Balance sheet capital | F57: Year | G57: 2022 | H57: 2023 | I57: 2024
B58: 2022 | C58: 2023 | D58: 2024 | F58: Debt ratio | G58: =B60/B59 -> 0.35736754 | H58: =C60/C59 -> 0.37709376 | I58: =D60/D59 -> 0.43712625
A59: Total Assets | B59: 17377161315995 | C59: 18111796269189 | D59: 20311783916069 | F59: Equity ratio | G59: =B73/B59 -> 0.64263246 | H59: =C73/C59 -> 0.62290624 | I59: =D73/D59 -> 0.56287375
A60: Liabilities | B60: 6210033388769 | C60: 6829845298714 | D60: 8878813931686 | F60: Total Debt (trillion VND) | G60: =6210033388769/1000000000000 -> 6.2100334 | H60: =6829845298714/1000000000000 -> 6.8298453 | I60: =8878813931686/1000000000000 -> 8.8788139
A61: Current Liabilities | B61: 6195799689582 | C61: 6815609482547 | D61: 8864853420561 | F61: Debt growth | G61: - | H61: =(H60/G60)-1 -> 0.099808145 | I61: =(I60/H60)-1 -> 0.3000022
A62: Accounts Payable | B62: 1970635586928 | C62: 3330483232614 | D62: 2853606214481 | F62: Total Equity (trillion VND) | G62: =11167127927226/1000000000000 -> 11.167128 | H62: =11281950970475/1000000000000 -> 11.281951 | I62: =11432969984383/1000000000000 -> 11.43297
A63: Advances from Customers | B63: 176845202295 | C63: 129957335766 | D63: 179998887975 | F63: D/E ratio | G63: =G60/G62 -> 0.55609942 | H63: =H60/H62 -> 0.60537803 | I63: =I60/I62 -> 0.77659733
A64: Taxes and Other Payables to the State | B64: 5275868275 | C64: 145505586644 | D64: 74417109924 | F64: Total Assets (trillion VND) | G64: =17377161315995/1000000000000 -> 17.377161 | H64: =18111796269189/1000000000000 -> 18.111796 | I64: =20311783916069/1000000000000 -> 20.311784
A65: Employee Payables | B65: 64245590725 | C65: 48600453107 | D65: 64468071697 | F65: ST Debt (trillion VND) | G65: =6195799689582/1000000000000 -> 6.1957997 | H65: =6815609482547/1000000000000 -> 6.8156095 | I65: =8864853420561/1000000000000 -> 8.8648534
A66: Accrued Expenses | B66: 207561319455 | C66: 66684028030 | D66: 208807717032 | F66: LT Debt (trillion VND) | G66: =14233699187/1000000000000 -> 0.014233699 | H66: =14235816167/1000000000000 -> 0.014235816 | I66: =13960511125/1000000000000 -> 0.013960511
A67: Other Current Payables | B67: 18979145366 | C67: 42122470287 | D67: 137451191503
A68: Short-term Borrowings | B68: 3545557150716 | C68: 2903786802438 | D68: 5310715159144
A69: Bonus and Welfare Fund | B69: 4 | C69: 148469573661 | D69: 35388068805
A70: Non-current Liabilities | B70: 14233699187 | C70: 14235816167 | D70: 13960511125
A71: Other Long-term Payables | B71: 709500000 | C71: 709500000 | D71: 709500000
A72: Long-term Provisions | B72: 13524199187 | C72: 13526316167 | D72: 13251011125
A73: Equity | B73: 11167127927226 | C73: 11281950970475 | D73: 11432969984383
A74: Owners' Equity | B74: 11167127927226 | C74: 11281950970475 | D74: 11432969984383
A75: Contributed Capital | B75: 5980549860000 | C75: 6159823090000 | D75: 6159823090000
A76: Ordinary Shares | B76: 5980549860000 | C76: 6159823090000 | D76: 6159823090000
A77: Share Premium | B77: 157292539068 | C77: 157292539068 | D77: 157292539068
A78: Other Equity Funds | B78: 187499009876 | C78: 77910496944 | D78: 50993213769
... A82: Total Liabilities and Equity | B82: 17377161315995 | C82: 18111796269189 | D82: 20311783916069
A84: Income statement
C85: 2022 | D85: 2023 | E85: 2024 | G85: Year | H85: 2022 | I85: 2023 | J85: 2024
A86: Revenue from sales and service provision | C86: 81450228213277 | D86: 52881019564133 | E86: 67051370845971 | G86: Revenue (trillion VND) | H86: =81189481215099/1000000000000 -> 81.189481 | I86: =52604763167190/1000000000000 -> 52.604763 | J86: =66712547798751/1000000000000 -> 66.712548
A87: Sales deductions | C87: 260746998178 | D87: 276256396943 | E87: 338823047220 | G87: Revenue growth(%) | H87: - | I87: =I86/H86 -1 -> -0.35207416 | J87: =J86/I86 -1 -> 0.26818455
A88: Net revenue from sales and service provision | C88: 81189481215099 | D88: 52604763167190 | E88: 66712547798751 | G88: Net profit (trillion VND) | H88: =48170557444/1000000000000 -> 0.048170557 | I88: =248288982544/1000000000000 -> 0.24828898 | J88: =528922307162/1000000000000 -> 0.52892231
A89: Cost of goods sold and services provided | C89: 77388423409761 | D89: 50476627454498 | E89: 63473799048283 | G89: Profit growth (%) | H89: - | I89: =I88/H88-1 -> 4.1543722 | J89: =J88/I88-1 -> 1.1302689
A90: Gross profit (20 = 10 - 11) | C90: 3801057805338 | D90: 2128135712692 | E90: 3238748750468 | G90: General and administrative expenses | H90: =323017357209/1000000000000 -> 0.32301736 | I90: =242553285595/1000000000000 -> 0.24255329 | J90: =308367699972/1000000000000 -> 0.3083677
A91: Financial income | C91: 425167604879 | D91: 800850256543 | E91: 652938094707 | G91: Selling expenses | H91: =3469159524662/1000000000000 -> 3.4691595 | I91: =2121829595199/1000000000000 -> 2.1218296 | J91: =2858708812560/1000000000000 -> 2.8587088
A92: Financial expenses | C92: 419889233636 | D92: 300217604297 | E92: 251550025718 | G92: Cost of goods sold and services provided | H92: =77388423409761/1000000000000 -> 77.388423 | I92: =50476627454498/1000000000000 -> 50.476627 | J92: =63473799048283/1000000000000 -> 63.473799
A93: Selling expenses | C93: 3469159524662 | D93: 2121829595199 | E93: 2858708812560 | G93: Financial expenses | H93: =419889233636/1000000000000 -> 0.41988923 | I93: =300217604297/1000000000000 -> 0.3002176 | J93: =251550025718/1000000000000 -> 0.25155003
A94: General and administrative expenses | C94: 323017357209 | D94: 242553285595 | E94: 308367699972 | G94: Administrative Expense % | H94: =H90/H86 -> 0.0039785617 | I94: =I90/I86 -> 0.0046108617 | J94: =J90/J86 -> 0.0046223343
A95: Operating profit | C95: 14159294710 | D95: 264385484144 | E95: 473060306925 | G95: Selling Expense % | H95: =H91/H86 -> 0.042729175 | I95: =I91/I86 -> 0.040335313 | J95: =J91/J86 -> 0.042851141
A96: Other income | C96: 37281371157 | D96: 45338320487 | E96: 34684261898 | G96: Financial Expenses % | H96: =H93/H86 -> 0.0051717196 | I96: =I93/I86 -> 0.0057070422 | J96: =J93/J86 -> 0.0037706554
A97: Other expenses | C97: 2028544004 | D97: 631991708 | E97: 5192249642 | G97: COGS % | H97: =H92/H86 -> 0.95318288 | I97: =I92/I86 -> 0.95954481 | J97: =J92/J86 -> 0.95145218
A98: Other profit/(loss) (40 = 31 - 32) | C98: 35252827153 | D98: 44706328779 | E98: 29492012256 | G98: Gross Margin % | H98: =1-H97 -> 0.046817121 | I98: =1-I97 -> 0.04045519 | J98: =1-J97 -> 0.04854782
A99: Total accounting profit before tax (50 = 30 + 40) | C99: 49412121863 | D99: 309091812923 | E99: 502552319181
A100: Current corporate income tax expense | C100: 23681645484 | D100: 1536979754 | E100: 99693200
A101: Deferred corporate income tax benefit | C101: -22440081065 | D101: 59265850625 | E101: 26469681181
A102: Net profit after corporate income tax (60 = 50 - 51 - 52) | C102: 48170557444 | D102: 248288982544 | E102: 528922307162
C103: Thuyết minh số 27(b) BCTC HSG 2022 | D103: Thuyết minh số 4(b) BCTC HSG 2023 | E103: Thuyết minh số 34(b) BCTC HSG 2024
A104: Items | B104: Geographic Segment | C104: 2022 | D104: 2023 | E104: 2024
A105: Net Revenue | B105: International | C105: =24974529436439/1000000000000 -> 24.974529 | D105: =13011102718508/1000000000000 -> 13.011103 | E105: =18668429521777/1000000000000 -> 18.66843
B106: Domestic | C106: =56214951778660/1000000000000 -> 56.214952 | D106: =39593660448682/1000000000000 -> 39.59366 | E106: =48044118276974/1000000000000 -> 48.044118
B107: International | C107: =C105/C109 -> 0.30760794 | D107: =D105/D109 -> 0.24733697 | E107: =E105/E109 -> 0.27983386
B108: Domestic | C108: =C106/C109 -> 0.69239206 | D108: =D106/D109 -> 0.75266303 | E108: =E106/E109 -> 0.72016614
...

Sheet 3. Financing
B2: 1. Fund mobilization parttcipants | D2: 1.1. Creditors | J2: 1.2. Suppliers | P2: 1.3. Government / Tax Authorities | V2: 1.4. Key owners | Z2: 1.5. Share holders | AN2: 4. Cost of capital
D3: Banks | E3: 2022 | F3: 2023 | G3: 2024 | J3: Company | K3: 2022 | L3: 2023 | M3: 2024 | Q3: 2022 | R3: 2023 | S3: 2024 | W3: % of Equity | AA3: 2022 | AB3: 2023 | AC3: 2024
D4: Vietcombank | E4: 1489725213974 | F4: 1100416059001 | G4: 2647446645284 | J4: Accounts payable | K4: ='Balance Sheet'!D45 -> 1970635586928 | L4: ='Balance Sheet'!E45 -> 3330483232614 | M4: ='Balance Sheet'!F45 -> 2853606214481 | P4: Taxes and Other Payables to the State Budget | Q4: ='Balance Sheet'!D47 -> 5275868275 | R4: ='Balance Sheet'!E47 -> 145505586644 | S4: ='Balance Sheet'!F47 -> 74417109924 | V4: Mr. Le Phuoc Vu | W4: 17,02% | Z4: Share dividends (shares) | AA4: 99672290 | AB4: 17927323 | AC4: -
D5: Vietinbank | E5: 1367294386632 | F5: 1625599905996 | G5: 2271483187659 | V5: Other stakeholders | W5: 82,98% | Z5: ESOP | AA5: 4900800000 | AB5: - | AC5: 5000000 | AO5: FUNDING | BE5: OPERATION RESULTS OF INVESTMENT
D6: BIDV | E6: - | F6: - | G6: 323755954476 | V6: Notes of FSs | W6: 21b | Z6: Notes of FSs | AA6: 24(i), (ii) | AB6: 24(i) | AC6: 37(a) | AN6: Liabilities | BD6: Revenues + Incomes
D7: HSBC | E7: 421607418953 | F7: - | G7: - | AN7: Mã số | AO7: NỢ PHẢI TRẢ (300 = 310 + 330) | AP7: Liabilities | AQ7: Thuyết minh | AR7: 30/9/2022 (VND) | AS7: 30/9/2023 (VND) | AT7: 30/9/2024 (VND) | AU7: 44469 | BD7: Mã số | BE7: Chỉ tiêu | BF7: Eng | BG7: Thuyết minh | BH7: 30/9/2022 (VND) | BI7: 30/9/2023 (VND) | BJ7: 30/9/2024 (VND)
D8: Kasikornbank | E8: - | F8: 177770837441 | G8: 15029371725 | AN8: 300 | AO8: NỢ PHẢI TRẢ | AP8: Total Liabilities | AR8: 6210033388769 | AS8: 6829845298714 | AT8: 8878813931686 | AU8: 13195700411669 | BD8: 1 | BE8: Doanh thu bán hàng và cung cấp dịch vụ | BF8: Revenue from sales and service provision | BG8: 27 | BH8: 81450228213277 | BI8: 52881019564133 | BJ8: 67051370845971
D9: UOB | E9: 266930131158 | F9: - | G9: 53000000000 | AN9: 310 | AO9: Nợ ngắn hạn | AP9: Current Liabilities | AR9: 6195799689582 | AS9: 6815609482547 | AT9: 8864853420561 | BD9: 2 | BE9: Các khoản giảm trừ doanh thu | BF9: Sales deductions | BG9: 27 | BH9: 260746998178 | BI9: 276256396943 | BJ9: 338823047220
D10: Notes of FSs | E10: 21 | F10: 21 | G10: 18 | AN10: 311 | AO10: Phải trả người bán | AP10: Accounts Payable | AQ10: 17 | AR10: 1970635586928 | AS10: 3330483232614 | AT10: 2853606214481 | AX10: 2022 | AY10: 2023 | AZ10: 2024 | BD10: 10 | BE10: Doanh thu thuần về bán hàng và cung cấp dịch vụ | BF10: Net revenue from sales and service provision | BG10: 27 | BH10: 81189481215099 | BI10: 52604763167190 | BJ10: 66712547798751
D11: total | E11: =SUM(E4:E9) -> 3545557150717 | F11: =SUM(F4:F9) -> 2903786802438 | G11: =SUM(G4:G9) -> 5310715159144 | AN11: 312 | AO11: Người mua trả tiền trước | AP11: Advances from Customers | AR11: 176845202295 | AS11: 129957335766 | AT11: 179999887975 | AW11: %D = Liability / ( L+OE) | AX11: =AR8/(AR8+AR24) -> 0.35736754 | AY11: =AS8/(AS8+AS24) -> 0.37709376 | AZ11: =AT8/(AT8+AT24) -> 0.43712625 | BD11: 11 | BE11: Giá vốn hàng bán và dịch vụ cung cấp | BF11: Cost of goods sold and services provided | BG11: 28 | BH11: 77388423409761 | BI11: 50476627454498 | BJ11: 63473799048283
B12: 2. Liabilities | D12: 2.1. Short-term Liabilities | J12: 2022 | K12: 2023 | L12: 2024 | N12: 2.1.2. Long-term Libabilities | S12: 2.1.3. Creditor Composition | AN12: 313 | AO12: Thuế phải nộp Nhà nước | AP12: Taxes and Other Payables to the State Budget | AQ12: 18(a) | AR12: 5275868275 | AS12: 145505586644 | AT12: 74417109924 | AW12: %OE = 100% - %D | AX12: =100%-AX11 -> 0.64263246 | AY12: =100%-AY11 -> 0.62290624 | AZ12: =100%-AZ11 -> 0.56287375 | BD12: 20 | BE12: Lợi nhuận gộp (20 = 10 - 11) | BF12: Gross profit (20 = 10 - 11) | BH12: 3801057805338 | BI12: 2128135712692 | BJ12: 3238748750468
E13: Total Liabilities | F13: Total Interest-free Capital | G13: %i | I13: Accounts Payable | J13: =AR10 -> 1970635586928 | K13: =AS10 -> 3330483232614 | L13: =AT10 -> 2853606214481 | O13: 2022 | P13: 2023 | Q13: 2024 | S13: Credit group | T13: 2022 | U13: % | V13: 2023 | W13: % | X13: 2024 | Y13: % | AN13: 314 | AO13: Phải trả người lao động | AP13: Employee Payables | AR13: 64245590725 | AS13: 48600453107 | AT13: 64468071697 | AW13: CIT=Tax paid/ NI before tax | AX13: =(BH23+BH24)/BH22 -> 0.025126717 | AY13: =(BI23+BI24)/BI22 -> 0.19671446 | AZ13: =(BJ23+BJ24)/BJ22 -> 0.052868872 | BD13: 21 | BE13: Doanh thu hoạt động tài chính | BF13: Financial income | BG13: 29 | BH13: 425167604879 | BI13: 800850256543 | BJ13: 652938094707
D14: 2022 | E14: =AR8 -> 6210033388769 | F14: =J20 -> 2650242538866 | G14: =ROUND(F14/E14*100, 2) -> 42.68 | I14: Advances from Customers | J14: =AR11 -> 176845202295 | K14: =AS11 -> 129957335766 | L14: =AT11 -> 179999887975 | N14: Current Liabilities | O14: =AR9 -> 6195799689582 | P14: =AS9 -> 6815609482547 | Q14: =AT9 -> 8864853420561 | S14: Bank | T14: =E11 -> 3545557150717 | U14: =ROUND(T14/T17*100,2) -> 64.21 | V14: =F11 -> 2903786802438 | W14: =ROUND(V14/V17*100,2) -> 45.52 | X14: =G11 -> 5310715159144 | Y14: =ROUND(X14/X17*100,2) -> 64.46 | AN14: 315 | AO14: Chi phí phải trả | AP14: Accrued Expenses | AQ14: 19 | AR14: 207561319455 | AS14: 66684028030 | AT14: 208807717032 | AW14: Rd=Interest paid/ averaged Liabilities | AX14: =BH15/((AR8+AU8)/2) -> 0.018192402 | AY14: =BI15/((AR8+AS8)/2) -> 0.0283277 | AZ14: =BJ15/((AS8+AT8)/2) -> 0.016781191 | BD14: 22 | BE14: Chi phí tài chính | BF14: Financial expenses | BG14: 30 | BH14: 419889233636 | BI14: 300217604297 | BJ14: 251550025718
D15: 2023 | E15: =AS8 -> 6829845298714 | F15: =K20 -> 3911822680109 | G15: =ROUND(F15/E15*100, 2) -> 57.28 | I15: Taxes and Other Payables to the State Budget | J15: =AR12 -> 5275868275 | K15: =AS12 -> 145505586644 | L15: =AT12 -> 74417109924 | N15: Long-term Liabilities | O15: =AR18 -> 14233699187 | P15: =AS18 -> 14235816167 | Q15: =AT18 -> 13960511125 | S15: Supplier | T15: =T27 -> 1970635586928 | U15: =ROUND(T15/T17*100,2) -> 35.69 | V15: =U27 -> 3330483232614 | W15: =ROUND(V15/V17*100,2) -> 52.2 | X15: =V27 -> 2853606214481 | Y15: =ROUND(X15/X17*100,2) -> 34.64 | AN15: 319 | AO15: Phải trả ngắn hạn khác | AP15: Other Short-term Payables | AQ15: 20 | AR15: 18979145366 | AS15: 42122470287 | AT15: 137451191503 | AW15: Rf | AX15: 0.032 | AY15: 0.028 | AZ15: 0.034 | BA15: vietstock hsg | BD15: 23 | BE15: Trong đó: Chi phí lãi vay | BF15: Of which: Interest expenses | BH15: 176518452634 | BI15: 184694883045 | BJ15: 131805003372
D16: 2024 | E16: =AT8 -> 8878813931686 | F16: =L20 -> 3554138261417 | G16: =ROUND(F16/E16*100, 2) -> 40.03 | I16: Employee Payables | J16: =AR13 -> 64245590725 | K16: =AS13 -> 48600453107 | L16: =AT13 -> 64468071697 | N16: Total Liabilities | O16: =AR8 -> 6210033388769 | P16: =AS8 -> 6829845298714 | Q16: =AT8 -> 8878813931686 | S16: Government | T16: =Q4 -> 5275868275 | U16: =ROUND(T16/T17*100,2) -> 0.1 | V16: =R4 -> 145505586644 | W16: =ROUND(V16/V17*100,2) -> 2.28 | X16: =S4 -> 74417109924 | Y16: =ROUND(X16/X17*100,2) -> 0.9 | AN16: 320 | AO16: Vay ngắn hạn | AP16: Short-term Borrowings | AQ16: 21 | AR16: 3545557150716 | AS16: 2903786802438 | AT16: 5310715159144 | AW16: Beta | AX16: 1.9 | AY16: 2.22 | AZ16: 1.7 | BD16: 25 | BE16: Chi phí bán hàng | BF16: Selling expenses | BG16: 31 | BH16: 3469159524662 | BI16: 2121829595199 | BJ16: 2858708812560
I17: Accrued Expenses | J17: =AR14 -> 207561319455 | K17: =AS14 -> 66684028030 | L17: =AT14 -> 208807717032 | N17: i% | O17: =ROUND(O14/O16*100,2) -> 99.77 | P17: =ROUND(P14/P16*100,2) -> 99.79 | Q17: =ROUND(Q14/Q16*100,2) -> 99.84 | S17: Total | T17: =SUM(T14:T16) -> 5521468605920 | U17: 100 | V17: =SUM(V14:V16) -> 6379775621696 | W17: 100 | X17: =SUM(X14:X16) -> 8238738483549 | Y17: 100 | AN17: 322 | AO17: Quỹ khen thưởng, phúc lợi | AP17: Bonus and Welfare Fund | AQ17: 22 | AR17: 206699825822 | AS17: 148469573661 | AT17: 35388068805 | AW17: Risk premium | AX17: 0.0957 | AY17: 0.0779 | AZ17: 0.0866 | BD17: 26 | BE17: Chi phí quản lý doanh nghiệp | BF17: General and administrative expenses | BG17: 32 | BH17: 323017357209 | BI17: 242553285595 | BJ17: 308367699972
I18: Other Short-term Payables | J18: =AR15 -> 18979145366 | K18: =AS15 -> 42122470287 | L18: =AT15 -> 137451191503 | O18: =ROUND(O15/O16*100,2) -> 0.23 | P18: =ROUND(P15/P16*100,2) -> 0.21 | Q18: =ROUND(Q15/Q16*100,2) -> 0.16 | AN18: 330 | AO18: Nợ dài hạn | AP18: Long-term Liabilities | AR18: 14233699187 | AS18: 14235816167 | AT18: 13960511125 | AW18: Re=Rf+Beta*Risk pre | AX18: =AX15+(AX16*AX17) -> 0.21383 | AY18: =AY15+(AY16*AY17) -> 0.200938 | AZ18: =AZ15+(AZ16*AZ17) -> 0.18122 | BD18: 30 | BE18: Lợi nhuận thuần từ hoạt động kinh doanh | BF18: Operating profit | BH18: 14159294710 | BI18: 264385484144 | BJ18: 473060306925
I19: Bonus and Welfare Fund | J19: =AR17 -> 206699825822 | K19: =AS17 -> 148469573661 | L19: =AT17 -> 35388068805 | S19: Supplier | T19: 2022 (VND) | U19: 2023 (VND) | V19: 2024 (VND) | W19: 2022 (%) | X19: 2023 (%) | Y19: 2024 (%) | AN19: 337 | AO19: Phải trả dài hạn khác | AP19: Other Long-term Payables | AR19: 709500000 | AS19: 709500000 | AT19: 709500000 | AW19: (WACC)= %D*Rd*(1-CIT) + %OE* Re | AX19: =AX11*AX14*(1-AX13)+AX12*AX18 -> 0.14375211 | AY19: =AY11*AY14*(1-AY13)+AY12*AY18 -> 0.13374639 | AZ19: =AZ11*AZ14*(1-AZ13)+AZ12*AZ18 -> 0.10895166 | BD19: 31 | BE19: Thu nhập khác | BF19: Other income | BH19: 37281371157 | BI19: 45338320487 | BJ19: 34684261898
I20: Total interest-free capital | J20: =SUM(J13:J19) -> 2650242538866 | K20: =SUM(K13:K19) -> 3911822680109 | L20: =SUM(L13:L19) -> 3554138261417 | S20: Win Faith Trading Limited | T20: - | U20: 1060712721850 | V20: - | W20: - | X20: =ROUND(U20/U27*100,2) -> 31.85 | Y20: - | AN20: 342 | AO20: Dự phòng phải trả dài hạn | AP20: Long-term Provisions | AQ20: 23 | AR20: 13524199187 | AS20: 13526316167 | AT20: 13251011125 | BD20: 32 | BE20: Chi phí khác | BF20: Other expenses | BH20: 2028544004 | BI20: 631991708 | BJ20: 5192249642
S21: HSG Bình Định | T21: 458751657862 | U21: 334337182195 | V21: - | W21: =ROUND(T21/T27*100,2) -> 23.28 | X21: =ROUND(U21/U27*100,2) -> 10.04 | Y21: - | BD21: 40 | BE21: Lợi nhuận/(lỗ) khác (40 = 31 - 32) | BF21: Other profit/(loss) (40 = 31 - 32) | BH21: 35252827153 | BI21: 44706328779 | BJ21: 29492012256
S22: HSG Nhơn Hội | T22: 466964809368 | U22: 253940389459 | V22: - | W22: =ROUND(T22/T27*100,2) -> 23.7 | X22: =ROUND(U22/U27*100,2) -> 7.62 | Y22: - | AN22: Equity | BD22: 50 | BE22: Tổng lợi nhuận kế toán trước thuế (50 = 30 + 40) | BF22: Total accounting profit before tax (50 = 30 + 40) | BH22: 49412121863 | BI22: 309091812923 | BJ22: 502552319181
D23: ST borrowings | E23: =AR16 -> 3545557150716 | F23: =AS16 -> 2903786802438 | G23: =AT16 -> 5310715159144 | S23: HSG Hà Nam | T23: 205051386730 | U23: 111279330138 | V23: - | W23: =ROUND(T23/T27*100,2) -> 10.41 | X23: =ROUND(U23/U27*100,2) -> 3.34 | Y23: - | AN23: Mã số | AO23: VỐN CHỦ SỞ HỮU (400 = 410) | AP23: Total Equity (400 = 410) | AQ23: Thuyết minh | AR23: 30/9/2022 (VND) | AS23: 30/9/2023 (VND) | AT23: 30/9/2024 (VND) | BD23: 51 | BE23: Chi phí thuế TNDN hiện hành | BF23: Current corporate income tax expense | BG23: 34 | BH23: 23681645484 | BI23: 1536979754 | BJ23: 99693200
D24: Total Liabilities | E24: =AR8 -> 6210033388769 | F24: =AS8 -> 6829845298714 | G24: =AT8 -> 8878813931686 | S24: Gang Thép Hưng Nghiệp Formosa Hà Tĩnh | T24: 484333050520 | U24: 215321324077 | V24: - | W24: =ROUND(T24/T27*100,2) -> 24.58 | X24: =ROUND(U24/U27*100,2) -> 6.47 | Y24: - | AN24: 400 | AO24: VỐN CHỦ SỞ HỮU | AP24: Equity | AR24: 11167127927226 | AS24: 11281950970475 | AT24: 11432969984383 | BD24: 52 | BE24: Lợi ích thuế TNDN hoãn lại | BF24: Deferred corporate income tax benefit | BG24: 34 | BH24: -22440081065 | BI24: 59265850625 | BJ24: 26469681181
D25: ST Loans (i%) | E25: =ROUND(E23/E24*100,2) -> 57.09 | F25: =ROUND(F23/F24*100,2) -> 42.52 | G25: =ROUND(G23/G24*100,2) -> 59.81 | S25: Thép Kim Quốc | T25: - | U25: 148774386772 | V25: 603635726823 | W25: - | X25: =ROUND(U25/U27*100,2) -> 4.47 | Y25: =ROUND(V25/V27*100,2) -> 21.15 | AN25: 410 | AO25: Vốn chủ sở hữu | AP25: Owners' Equity | AQ25: 24 | AR25: 11167127927226 | AS25: 11281950970475 | AT25: 11432969984383 | BD25: 60 | BE25: Lợi nhuận thuần sau thuế TNDN (60 = 50 - 51 - 52) | BF25: Net profit after corporate income tax (60 = 50 - 51 - 52) | BH25: 48170557444 | BI25: 248288982544 | BJ25: 528922307162
S26: Thép Hòa Phát Dung Quất | T26: - | U26: 29420508150 | V26: 382563821530 | W26: - | X26: =ROUND(U26/U27*100,2) -> 0.88 | Y26: =ROUND(V26/V27*100,2) -> 13.41 | AN26: 411 | AO26: Vốn cổ phần | AP26: Share Capital | AQ26: 25 | AR26: 5980549860000 | AS26: 6159823090000 | AT26: 6159823090000
S27: Tổng | T27: 1970635586928 | U27: 3330483232614 | V27: 2853606214481 | W27: 100 | X27: 100 | Y27: 100 | AN27: 411a | AO27: - Cổ phiếu phổ thông có quyền biểu quyết | AP27: Common Shares with Voting Rights | AR27: 5980549860000 | AS27: 6159823090000 | AT27: 6159823090000 | BD27: Costs
S28: Khác | W28: =W27-SUM(W20:W26) -> 18.03 | X28: =X27-SUM(X20:X26) -> 35.33 | Y28: =Y27-SUM(Y20:Y26) -> 65.44 | AN28: 412 | AO28: Thặng dư vốn cổ phần | AP28: Share Premium | AR28: 157292539068 | AS28: 157292539068 | AT28: 157292539068 | BD28: Mã số | BE28: Chỉ tiêu | BF28: Eng | BG28: Thuyết minh | BH28: 30/9/2022 (VND) | BI28: 30/9/2023 (VND) | BJ28: 30/9/2024 (VND)
S29: Notes of FSs | T29: 17(a) | U29: 17(a) | V29: 13 | AN29: 420 | AO29: Quỹ khác thuộc vốn chủ sở hữu | AP29: Other Equity Funds | AR29: 187499009876 | AS29: 77910496944 | AT29: 50993213769 | BD29: 11 | BE29: Giá vốn hàng bán và dịch vụ cung cấp | BF29: Cost of goods sold and services provided | BG29: 28 | BH29: 77388423409761 | BI29: 50476627454498 | BJ29: 63473799048283
AN30: 421 | AO30: Lợi nhuận sau thuế chưa phân phối | AP30: Retained Earnings | AR30: 4841786518282 | AS30: 4886924844463 | AT30: 5064861141546 | BD30: 22 | BE30: Chi phí tài chính | BF30: Financial expenses | BG30: 30 | BH30: 419889233636 | BI30: 300217604297 | BJ30: 251550025718
AN31: 421a | AO31: - LNST chưa phân phối đến cuối năm trước | AP31: Retained Earnings at the End of Previous Year | AR31: 4793615960838 | AS31: 4638635861919 | AT31: 4576082907573 | BD31: 23 | BE31: Trong đó: Chi phí lãi vay | BF31: Of which: Interest expenses | BH31: 176518452634 | BI31: 184694883045 | BJ31: 131805003372
AN32: 421b | AO32: - LNST chưa phân phối năm nay | AP32: Retained Earnings of the Current Year | AR32: 48170557444 | AS32: 248288982544 | AT32: 488778233973 | BD32: 25 | BE32: Chi phí bán hàng | BF32: Selling expenses | BG32: 31 | BH32: 3469159524662 | BI32: 2121829595199 | BJ32: 2858708812560
D33: 2.2. Owner's Equity | J33: 2.3. Cost of Liabilities Financing | BD33: 26 | BE33: Chi phí quản lý doanh nghiệp | BF33: General and administrative expenses | BG33: 32 | BH33: 323017357209 | BI33: 242553285595 | BJ33: 308367699972
E34: 2022 | F34: 2023 | G34: 2024 | K34: 2022 | L34: 2023 | M34: 2024 | BD34: 32 | BE34: Chi phí khác | BF34: Other expenses | BH34: 2028544004 | BI34: 631991708 | BJ34: 5192249642
D35: Total Equity | E35: =AR25 -> 11167127927226 | F35: =AS25 -> 11281950970475 | G35: =AT25 -> 11432969984383 | J35: Interest expenses | K35: =BH31 -> 176518452634 | L35: =BI31 -> 184694883045 | M35: =BJ31 -> 131805003372 | BD35: 51 | BE35: Chi phí thuế TNDN hiện hành | BF35: Current corporate income tax expense | BG35: 34 | BH35: 23681645484 | BI35: 1536979754 | BJ35: 99693200
D36: Owner's Equity | E36: =E35 -> 11167127927226 | F36: =F35 -> 11281950970475 | G36: =G35 -> 11432969984383 | J36: EBIT | K36: =BH43+K35 -> 225930574497 | L36: =BI43+L35 -> 493786695968 | M36: =BJ43+M35 -> 634357322553
D37: Retained Earnings | E37: =AR30 -> 4841786518282 | F37: =AS30 -> 4886924844463 | G37: =AT30 -> 5064861141546 | J37: ICR | K37: =ROUND(K36/K35,2) -> 1.28 | L37: =ROUND(L36/L35,2) -> 2.67 | M37: =ROUND(M36/M35,2) -> 4.81
D38: RE Ratio | E38: =ROUND(E37/E36*100,2) -> 43.36 | F38: =ROUND(F37/F36*100,2) -> 43.32 | G38: =ROUND(G37/G36*100,2) -> 44.3 | K38: =BH10-SUM(BH29:BH35) -> -613236952291 | BD38: Profit
K39: =ebit/interest | BD39: Mã số | BE39: Chỉ tiêu | BF39: Eng | BG39: Thuyết minh | BH39: 30/9/2022 (VND) | BI39: 30/9/2023 (VND) | BJ39: 30/9/2024 (VND)
K40: =BH25-BH23-K35 -> -152029540674 | BD40: 20 | BE40: Lợi nhuận gộp (20 = 10 - 11) | BF40: Gross profit (20 = 10 - 11) | BH40: 3801057805338 | BI40: 2128135712692 | BJ40: 3238748750468
K41: =BH43+K35 -> 225930574497 | BD41: 30 | BE41: Lợi nhuận thuần từ hoạt động kinh doanh | BF41: Operating profit | BH41: 14159294710 | BI41: 264385484144 | BJ41: 473060306925
BD42: 40 | BE42: Lợi nhuận/(lỗ) khác (40 = 31 - 32) | BF42: Other profit/(loss) (40 = 31 - 32) | BH42: 35252827153 | BI42: 44706328779 | BJ42: 29492012256
BD43: 50 | BE43: Tổng lợi nhuận kế toán trước thuế (50 = 30 + 40) | BF43: Total accounting profit before tax (50 = 30 + 40) | BH43: 49412121863 | BI43: 309091812923 | BJ43: 502552319181
B44: 3. Matching of fund structure | D44: 3.1. Financial Implications | J44: 3.2. Working capital Analysis | BD44: 60 | BE44: Lợi nhuận thuần sau thuế TNDN (60 = 50 - 51 - 52) | BF44: Net profit after corporate income tax (60 = 50 - 51 - 52) | BH44: 48170557444 | BI44: 248288982544 | BJ44: 528922307162
E45: 2022 | F45: 2023 | G45: 2024 | K45: 2022 | L45: 2023 | M45: 2024
D46: Non-current assets | E46: ='Balance Sheet'!D22 -> 5118727087531 | F46: ='Balance Sheet'!E22 -> 4924991584484 | G46: ='Balance Sheet'!F22 -> 4763897298254 | J46: WC | K46: ='Balance Sheet'!D3-'3. Financing'!AR9 -> 6062634538882 | L46: ='Balance Sheet'!E3-'3. Financing'!AS9 -> 6371195202158 | M46: ='Balance Sheet'!F3-'3. Financing'!AT9 -> 6683033197254
D47: Long-term funding | E47: =AR18+AR24 -> 11181361626413 | F47: =AS18+AS24 -> 11296186786642 | G47: =AT18+AT24 -> 11446930495508
O51: part 4 ->
E65: 2022 | F65: 2023 | G65: 2024
D66: Long-term Liabilities | E66: =AR18 -> 14233699187 | F66: =AS18 -> 14235816167 | G66: =AT18 -> 13960511125
D67: Owner's Equity | E67: =AR24 -> 11167127927226 | F67: =AS24 -> 11281950970475 | G67: =AT24 -> 11432969984383
B72: 5. Long-term Liabilities | C72: 5.1. Long-term Liabilities | D72: 5.1.1. ROC – Trend analysis | K72: 5.2. Owner's Equity | L72: 5.2.1. Tỷ suất sinh lời trên vốn chủ sở hữu (ROE) – Phân tích xu hướng
E73: 2022 | F73: 2023 | G73: 2024 | H73: 2021 | M73: 2022 | N73: 2023 | O73: 2024 | S73: HSG(2024) | T73: HPG(2024) | U73: NKG (2024)
D74: Interest expenses | E74: =BH15 -> 176518452634 | F74: =BI15 -> 184694883045 | G74: =BJ15 -> 131805003372 | L74: Net Income | M74: =BH44 -> 48170557444 | N74: =BI44 -> 248288982544 | O74: =BJ44 -> 528922307162 | R74: Net Income | S74: =O74 -> 528922307162 | T74: 10247400472100 | U74: 456063292961
D75: Total profit before tax | E75: =BH22 -> 49412121863 | F75: =BI22 -> 309091812923 | G75: =BJ22 -> 502552319181 | L75: Equity | M75: =AR24 -> 11167127927226 | N75: =AS24 -> 11281950970475 | O75: =AT24 -> 11432969984383 | R75: Average Equity | S75: =O76 -> 1.1375811e+13 | T75: 75790640877920 | U75: 5476820876106
D76: EBIT | E76: =E75+E74 -> 225930574497 | F76: =F75+F74 -> 493786695968 | G76: =G75+G74 -> 634357322553 | L76: Average Equity | M76: =AVERAGE(H81,M75) -> 11242889732266 | N76: =AVERAGE(H81,N75) -> 1.1300301e+13 | O76: =AVERAGE(H81,O75) -> 1.1375811e+13 | R76: ROE | S76: =S74/S75 -> 0.04649535 | T76: =T74/T75 -> 0.13520667 | U76: =U74/U75 -> 0.083271537
L77: ROE= NI/ averaged OE | M77: =M74/M76 -> 0.0042845353 | N77: =N74/N76 -> 0.021971891 | O77: =O74/O76 -> 0.04649535 | R77: resources | T77: FSs of HPG | U77: FSs of NKG
E79: 2022 | F79: 2023 | G79: 2024 | M79: 2022 | N79: 2023 | O79: 2024
D80: Long-term Liabilities | E80: =AR18 -> 14233699187 | F80: =AS18 -> 14235816167 | G80: =AT18 -> 13960511125 | H80: 13652557267 | I80: Balance sheet of FS 2022 | L80: ROE= NI/ averaged OE | M80: =M74/M76 -> 0.0042845353 | N80: =N74/N76 -> 0.021971891 | O80: =O74/O76 -> 0.04649535
D81: Equity | E81: =AR24 -> 11167127927226 | F81: =AS24 -> 11281950970475 | G81: =AT24 -> 11432969984383 | H81: 11318651537306
D82: Capital | E82: =SUM(E80:E81) -> 11181361626413 | F82: =SUM(F80:F81) -> 11296186786642 | G82: =SUM(G80:G81) -> 11446930495508 | H82: =SUM(H80:H81) -> 11332304094573
D83: Average Capital | E83: =AVERAGE(E82,H82) -> 11256832860493 | F83: =AVERAGE(F82,E82) -> 1.1238774e+13 | G83: =AVERAGE(F82,G82) -> 11371558641075
D84: ROC = EBIT/ Averaged Capital | E84: =E76/E83 -> 0.020070528 | F84: =F76/F83 -> 0.043935992 | G84: =G76/G83 -> 0.055784554
E86: 2022 | F86: 2023 | G86: 2024
D87: ROC = EBIT/ Averaged Capital | E87: =E76/E83 -> 0.020070528 | F87: =F76/F83 -> 0.043935992 | G87: =G76/G83 -> 0.055784554
B88: 6. Risk of Financing | D88: 6.1. (Daily Level) Liquidity Risk | J88: 6.2. (Annual obligations) Debt obligations' fulfilling | Q88: 6.3. Default risk ~ Bankruptcy
E89: 2022 | F89: 2023 | G89: 2024 | K89: 2022 | L89: 2023 | M89: 2024 | R89: 2022 | S89: 2023 | T89: 2024 | V89: WC = Current asset - Current liabilities
D90: Current Assets | E90: ='Balance Sheet'!D3 -> 12258434228464 | F90: ='Balance Sheet'!E3 -> 13186804684705 | G90: ='Balance Sheet'!F3 -> 15547886617815 | J90: EBIT | K90: =E76 -> 225930574497 | L90: =F76 -> 493786695968 | M90: =G76 -> 634357322553 | Q90: Working Capital | R90: ='Balance Sheet'!D3-'3. Financing'!AR9 -> 6062634538882 | S90: ='Balance Sheet'!E3-'3. Financing'!AS9 -> 6371195202158 | T90: ='Balance Sheet'!F3-'3. Financing'!AT9 -> 6683033197254 | V90: Market cap = market capitalization = No of outstanding stock * market price
D91: Current Liabilities | E91: =AR9 -> 6195799689582 | F91: =AS9 -> 6815609482547 | G91: =AT9 -> 8864853420561 | J91: Interest expenses | K91: =BH15 -> 176518452634 | L91: =BI15 -> 184694883045 | M91: =BJ15 -> 131805003372 | Q91: Total Assets | R91: ='Balance Sheet'!D3+'Balance Sheet'!D22 -> 17377161315995 | S91: ='Balance Sheet'!E3+'Balance Sheet'!E22 -> 18111796269189 | T91: ='Balance Sheet'!F3+'Balance Sheet'!F22 -> 20311783916069 | V91: Sales = Operation revenue + financial income + Other income
D92: Current liquidity ratio = Current assets/ Current liability | E92: =ROUND(E90/E91,2) -> 1.98 | F92: =ROUND(F90/F91,2) -> 1.93 | G92: =ROUND(G90/G91,2) -> 1.75 | J92: Interest Coverage Ratio (ICR) =EBIT/ interest paid | K92: =K90/K91 -> 1.2799261 | L92: =L90/L91 -> 2.6735267 | M92: =M90/M91 -> 4.8128471 | Q92: Retained Earnings | R92: =AR30 -> 4841786518282 | S92: =AS30 -> 4886924844463 | T92: =AT30 -> 5064861141546
D93: Inventories | E93: ='Balance Sheet'!D15 -> 3185372278891 | F93: ='Balance Sheet'!E15 -> 3749491109277 | G93: ='Balance Sheet'!F15 -> 3943145442782 | Q93: EBIT | R93: =E74+E75 -> 225930574497 | S93: =F74+F75 -> 493786695968 | T93: =G74+G75 -> 634357322553
D94: Quick liquidity ratio | E94: =(E90-E93)/E91 -> 1.4643892 | F94: =(F90-F93)/F91 -> 1.3846617 | G94: =(G90-G93)/G91 -> 1.3090731 | Q94: Market Cap | R94: =R95*R96 -> 8137734194502 | S94: =S95*S96 -> 11663009038606 | T94: =T95*T96 -> 12747753884755
D95: Cash and Cash Equivalents | E95: ='Cash flow Statement'!C37 -> 242815476591 | F95: ='Cash flow Statement'!D37 -> 501386999566 | G95: ='Cash flow Statement'!E37 -> 427778817941 | K95: 2022 | L95: 2023 | M95: 2024 | Q95: Closing Price | R95: 13607 | S95: 18934 | T95: 20695 | U95: Notes of FSs: 25 | W95: 2022 | X95: 2023 | Y95: 2024
D96: acid liquidity ratio = cash and equivalents / current liability | E96: =E95/E91 -> 0.039190337 | F96: =F95/F91 -> 0.073564514 | G96: =G95/G91 -> 0.0482556 | J96: EBIT | K96: 225930574497 | L96: 493786695968 | M96: 634357322553 | Q96: Number of Outstanding Shares | R96: 598054986 | S96: 615982309 | T96: 615982309 | V96: 1.2 | W96: =R90/R91 -> 0.34888521 | X96: =S90/S91 -> 0.35177048 | Y96: =T90/T91 -> 0.32902246
J97: Accumulated Depreciation | K97: 2779798381221 | L97: 3039859254081 | M97: 3184751243181 | Q97: Total Liabilities | R97: =AR8 -> 6210033388769 | S97: =AS8 -> 6829845298714 | T97: =AT8 -> 8878813931686 | V97: 1.4 | W97: =R92/R91 -> 0.27862931 | X97: =S92/S91 -> 0.26982 | Y97: =T92/T91 -> 0.2493558
J98: Accumulated Amortization | K98: 75490553004 | L98: 86989447935 | M98: 92813092849 | Q98: Sales | R98: =BH10+BH13+BH19 -> 81651930191135 | S98: =BI10+BI13+BI19 -> 53450951744220 | T98: =BJ10+BJ13+BJ19 -> 67400170155356 | V98: 3.3 | W98: =R93/R91 -> 0.013001581 | X98: =S93/S91 -> 0.027263265 | Y98: =T93/T91 -> 0.031231
J99: Annual principal payment obligation | K99: 33679445401829 | L99: 22061887581884 | M99: 28854393170251 | Q99: Altman Z score | R99: =SUMPRODUCT($V$96:$V$100,W96:W100) -> 6.336706 | S99: =SUMPRODUCT($V$96:$V$100,X96:X100) -> 4.8656013 | T99: =SUMPRODUCT($V$96:$V$100,Y96:Y100) -> 5.0267164 | V99: 0.6 | W99: =R94/R97 -> 1.3104171 | X99: =S94/S97 -> 1.7076535 | Y99: =T94/T97 -> 1.4357496
J100: Cash flow repayment capacity | K100: =SUM(K96:K98)/K99 -> 0.091486646 | L100: =SUM(L96:L98)/L99 -> 0.16411268 | M100: =SUM(M96:M98)/M99 -> 0.13557456 | Q100: Bond Interest | R100: 0.025 | S100: 0.028 | T100: 0.02 | U100: resource: Vietstock | V100: 1 | W100: =R98/R91 -> 4.6988072 | X100: =S98/S91 -> 2.9511679 | Y100: =T98/T91 -> 3.3182792
Q101: Bond Interest | R101: 0.03 | S101: 0.035 | T101: 0.028
Q102: Interest Coverage Ratio | R102: =K90/K91 -> 1.2799261 | S102: =L90/L91 -> 2.6735267 | T102: =M90/M91 -> 4.8128471
Q103: Credit Rating | R103: CCC | S103: B+ | T103: BBB
Q104: Default Spread | R104: 0.1157 | S104: 0.0455 | T104: 0.0242
Q105: Reasonable Cost of Debt | R105: =R100+R104 -> 0.1407 | S105: =S100+S104 -> 0.0735 | T105: =T100+T104 -> 0.0442
Q106: Reasonable Cost of Debt | R106: =R101+R104 -> 0.1457 | S106: =S101+S104 -> 0.0805 | T106: =T101+T104 -> 0.0522
Q107: Real Cost of Debt | R107: =BH15/((AR8+AU8)/2) -> 0.018192402 | S107: =BI15/((AR8+AS8)/2) -> 0.0283277 | T107: =BJ15/((AS8+AT8)/2) -> 0.016781191

Sheet 4. Investment
A1: I. Investment Strategy & Portfolio | H1: Mã số | I1: Chỉ tiêu | K1: 2021 | L1: 2022 | M1: 2023 | N1: 2024
A2: 1. Operation Investment Portfolio | H2: 100 | I2: TÀI SẢN NGẮN HẠN (current assets) | J2: Current Assets | K2: 19651184333706 | L2: 12258434228464 | M2: 13186804684705 | N2: 15547886617815
A3: Under-operation | C3: 2022 | D3: 2023 | E3: 2024 | H3: 110 | I3: Tiền và các khoản tương đương tiền | J3: Cash and Cash Equivalents | K3: 406017139417 | L3: 242815476591 | M3: 501386999566 | N3: 427778817941
A4: 1 | B4: Cash and Cash equivalents | C4: =L3 -> 242815476591 | D4: =M3 -> 501386999566 | E4: =N3 -> 427778817941 | H4: 111 | I4: Tiền | J4: Cash | K4: 405267139417 | L4: 242065476591 | M4: 500636999566 | N4: 426922790174
A5: 2 | B5: Accounts Receivables | C5: =L8 -> 8315127736295 | D5: =M8 -> 8405245948063 | E5: =N8 -> 10613408098640 | H5: 112 | I5: Các khoản tương đương tiền | J5: Cash Equivalents | K5: 750000000 | L5: 750000000 | M5: 750000000 | N5: 856027767
B6: In which: from customer | C6: =L9 -> 7934070297881 | D6: =M9 -> 7416195465814 | E6: =N9 -> 9337308709135 | H6: 120 | I6: Đầu tư tài chính ngắn hạn | J6: Short-term Financial Investments | K6: 5000000000 | L6: 5000000000 | M6: 20560958904 | N6: 21278737672
B7: Allowance for Doubtful Receivables | C7: =L13 -> -13707168589 | D7: =M13 -> -10773807954 | E7: =N13 -> -428638286 | H7: 123 | I7: Đầu tư nắm giữ đến ngày đáo hạn | J7: Held-to-Maturity Investments | K7: 5000000000 | L7: 5000000000 | M7: 20560958904 | N7: 21278737672
A8: 3 | B8: Inventories | C8: =L14 -> 3185372278891 | D8: =M14 -> 3749491109277 | E8: =N14 -> 3943145442782 | H8: 130 | I8: Các khoản phải thu ngắn hạn | J8: Short-term Accounts Receivables | K8: 11898280531814 | L8: 8315127736295 | M8: 8405245948063 | N8: 10613408098640
B9: Allowance for Inventory Write-down | C9: =L16 -> -192583414198 | D9: =M16 -> -127008960824 | E9: =N16 -> -121848817394 | H9: 131 | I9: Phải thu ngắn hạn của khách hàng | J9: Accounts Receivable from Customer | K9: 9335440945200 | L9: 7934070297881 | M9: 7416195465814 | N9: 9337308709135
A10: 4 | B10: Long-term Accounts Receivables | C10: =L22 -> 241195291600 | D10: =M22 -> 140931524246 | E10: =N22 -> 175741186200 | H10: 132 | I10: Trả trước cho người bán ngắn hạn | J10: Advances to Suppliers | K10: 59244726922 | L10: 95559044734 | M10: 26549614993 | N10: 535694209756
A11: 5 | B11: Fixed Asset | C11: =L25 -> 1198450061079 | D11: =M25 -> 1016313002019 | E11: =N25 -> 844402354164 | H11: 135 | I11: Phải thu về cho vay ngắn hạn | J11: Short-term Loans Receivable | K11: 68000000000 | L11: - | M11: 118500000000 | N11: 374000000000
A12: 5.1 | B12: Tangible Fixed Assets | C12: =SUM(C13:C14) -> 1014508752822 | D12: =SUM(D13:D14) -> 848743235444 | E12: =SUM(E13:E14) -> 666709132303 | H12: 136 | I12: Phải thu ngắn hạn khác | J12: Other Short-term Receivables | K12: 2449326144281 | L12: 299205562269 | M12: 854774675210 | N12: 366833818035
B13: Tangible Fixed Assets - Historical Cost | C13: =L27 -> 3794307134043 | D13: =M27 -> 3888602489525 | E13: =N27 -> 3851460375484 | H13: 137 | I13: Dự phòng phải thu ngắn hạn khó đòi | J13: Allowance for Doubtful Receivables | K13: -13731284589 | L13: -13707168589 | M13: -10773807954 | N13: -428638286
B14: Tangible Fixed Assets - Accumulated Depreciation | C14: =L28 -> -2779798381221 | D14: =M28 -> -3039859254081 | E14: =N28 -> -3184751243181 | H14: 140 | I14: Hàng tồn kho | J14: Inventories | K14: 6384320637756 | L14: 3185372278891 | M14: 3749491109277 | N14: 3943145442782
A15: 5.2 | B15: Intangible Fixed assets | C15: =SUM(C16:C17) -> 183941308257 | D15: =SUM(D16:D17) -> 167569766575 | E15: =SUM(E16:E17) -> 177693221861 | H15: 141 | I15: Hàng tồn kho | J15: Inventory | K15: 6464778720342 | L15: 3377955693089 | M15: 3876500070101 | N15: 4064994260176
B16: Intangible Fixed Assets - Historical Cost | C16: =L30 -> 259431861261 | D16: =M30 -> 254559214510 | E16: =N30 -> 270506314710 | H16: 149 | I16: Dự phòng giảm giá hàng tồn kho | J16: Allowance for Inventory Write-down | K16: -80458082586 | L16: -192583414198 | M16: -127008960824 | N16: -121848817394
B17: Intangible Fixed Assets - Accumulated Amortization | C17: =L31 -> -75490553004 | D17: =M31 -> -86989447935 | E17: =N31 -> -92813092849 | H17: 150 | I17: Tài sản ngắn hạn khác | J17: Other Current Assets | K17: 957566024719 | L17: 510118736687 | M17: 510119668895 | N17: 542275520780
A18: Under-construction | H18: 151 | I18: Chi phí trả trước ngắn hạn | J18: Short-term Prepaid Expenses | K18: 85590388401 | L18: 94748267020 | M18: 96483062965 | N18: 86974686528
A19: 6 | B19: Long-term Construction in Progress | C19: =L32 -> 106037865309 | D19: =M32 -> 27180502737 | E19: =N32 -> 9027013569 | H19: 152 | I19: Thuế GTGT được khấu trừ | J19: Deductible VAT | K19: 871962016601 | L19: 286790842330 | M19: 285106020138 | N19: 326902155004
A20: Out of operation / Others | H20: 153 | I20: Thuế và các khoản khác phải thu Nhà nước | J20: Taxes and Other Receivables from the State | K20: 13619717 | L20: 128579627337 | M20: 128530585792 | N20: 128398679248
A21: 7 | B21: Other short-term Assets | C21: =SUM(C22:C24) -> 510118736687 | D21: =SUM(D22:D24) -> 510119668895 | E21: =SUM(E22:E24) -> 542275520780 | H21: 200 | I21: TÀI SẢN DÀI HẠN (non-current assets) | J21: Non-current Assets | K21: 4863167615269 | L21: 5118727087531 | M21: 4924991584484 | N21: 4763897298254
B22: Short-term Prepaid Expenses | C22: =L18 -> 94748267020 | D22: =M18 -> 96483062965 | E22: =N18 -> 86974686528 | H22: 210 | I22: Các khoản phải thu dài hạn | J22: Long-term Accounts Receivables | K22: 178887837400 | L22: 241195291600 | M22: 140931524246 | N22: 175741186200
B23: Deductible VAT | C23: =L19 -> 286790842330 | D23: =M19 -> 285106020138 | E23: =N19 -> 326902155004 | H23: 215 | I23: Phải thu về cho vay dài hạn | J23: Long-term Loans Receivable | K23: - | L23: 70700000000 | M23: - | N23: -
B24: Taxes and Other Receivables from the State | C24: =L20 -> 128579627337 | D24: =M20 -> 128530585792 | E24: =N20 -> 128398679248 | H24: 216 | I24: Phải thu dài hạn khác | J24: Other Long-term Receivables | K24: 178887837400 | L24: 170495291600 | M24: 140931524246 | N24: 175741186200
A25: 8 | B25: Other long-term Assets | C25: =SUM(C26:C27) -> 179193869543 | D25: =SUM(D26:D27) -> 150716555482 | E25: =SUM(E26:E27) -> 139131656650 | H25: 220 | I25: Tài sản cố định | J25: Fixed Asset | K25: 1134208705003 | L25: 1198450061079 | M25: 1016313002019 | N25: 844402354164
B26: Long-term Prepaid Expenses | C26: =L39 -> 69639780740 | D26: =M39 -> 100428317304 | E26: =N39 -> 62373737291 | H26: 221 | I26: TSCĐ hữu hình | J26: Property, Plant and Equipment | K26: 936170702614 | L26: 1014508752822 | M26: 848743235444 | N26: 666709132303
B27: Deferred Income Tax Assets | C27: =L40 -> 109554088803 | D27: =M40 -> 50288238178 | E27: =N40 -> 76757919359 | H27: 222 | I27: Nguyên giá | J27: Historical Cost | K27: 3463673580489 | L27: 3794307134043 | M27: 3888602489525 | N27: 3851460375484
H28: 223 | I28: Giá trị hao mòn lũy kế | J28: Accumulated Depreciation | K28: -2527502877875 | L28: -2779798381221 | M28: -3039859254081 | N28: -3184751243181
A29: 2. Financial Investments Portfolio | H29: 227 | I29: TSCĐ vô hình | J29: Intangible Assets | K29: 198038002389 | L29: 183941308257 | M29: 167569766575 | N29: 177693221861
A30: 1 | B30: Short-term Financial Investments | C30: =C31 -> 5000000000 | D30: =D31 -> 20560958904 | E30: =E31 -> 21278737672 | H30: 228 | I30: Nguyên giá | J30: Historical Cost | K30: 259988428918 | L30: 259431861261 | M30: 254559214510 | N30: 270506314710
B31: Held-to-Maturity Investments | C31: =L7 -> 5000000000 | D31: =M7 -> 20560958904 | E31: =N7 -> 21278737672 | H31: 229 | I31: Giá trị hao mòn lũy kế | J31: Accumulated Amortization | K31: -61950426529 | L31: -75490553004 | M31: -86989447935 | N31: -92813092849
A32: 2 | B32: Long-term Financial Investments | C32: =SUM(C33:C35) -> 3393850000000 | D32: =SUM(D33:D35) -> 3589850000000 | E32: =SUM(E33:E35) -> 3595595087671 | H32: 240 | I32: Tài sản dở dang dài hạn | J32: Long-term Work in Progress | K32: 180277059193 | L32: 106037865309 | M32: 27180502737 | N32: 9027013569
B33: Held-to-Maturity Investments | C33: =L37 -> 16000000000 | D33: =M37 -> 1000000000 | E33: =N37 -> 1000000000 | H33: 242 | I33: Chi phí xây dựng cơ bản dở dang | J33: Construction in Progress (CIP) | K33: 180277059193 | L33: 106037865309 | M33: 27180502737 | N33: 9027013569
B34: Investment in Subsidiaries | C34: =L35 -> 3377850000000 | D34: =M35 -> 3588850000000 | E34: =N35 -> 3594595087671 | H34: 250 | I34: Đầu tư tài chính dài hạn | J34: Long-term Financial Investments | K34: 3244000000000 | L34: 3393850000000 | M34: 3589850000000 | N34: 3595595087671
B35: Investments in Associates | C35: =L36 -> - | D35: =M36 -> - | E35: =N36 -> - | H35: 251 | I35: Đầu tư vào công ty con | J35: Investments in Subsidiaries | K35: 3228000000000 | L35: 3377850000000 | M35: 3588850000000 | N35: 3594595087671
H36: 252 | I36: Đầu tư vào công ty liên kết | J36: Investments in Associates | K36: - | L36: - | M36: - | N36: -
A37: II. Investment Efficiency Performance | H37: 255 | I37: Đầu tư nắm giữ đến ngày đáo hạn | J37: Held-to-Maturity Investments | K37: 16000000000 | L37: 16000000000 | M37: 1000000000 | N37: 1000000000
A38: 1. Overall Assessment | H38: 260 | I38: Tài sản dài hạn khác | J38: Other Non-current Assets | K38: 125794013673 | L38: 179193869543 | M38: 150716555482 | N38: 139131656650
C39: 2021 | D39: 2022 | E39: 2023 | F39: 2024 | H39: 261 | I39: Chi phí trả trước dài hạn | J39: Long-term Prepaid Expenses | K39: 38680005935 | L39: 69639780740 | M39: 100428317304 | N39: 62373737291
B40: Current Asset (Book Value) | C40: =K2 -> 19651184333706 | D40: =L2 -> 12258434228464 | E40: =M2 -> 13186804684705 | F40: =N2 -> 15547886617815 | H40: 262 | I40: Tài sản thuế thu nhập hoãn lại | J40: Deferred Tax Assets | K40: 87114007738 | L40: 109554088803 | M40: 50288238178 | N40: 76757919359
B41: Non-current Asset (Book Value) | C41: =K21 -> 4863167615269 | D41: =L21 -> 5118727087531 | E41: =M21 -> 4924991584484 | F41: =N21 -> 4763897298254 | H41: 270 | I41: TỔNG TÀI SẢN | J41: Total Assets | K41: 24514351948975 | L41: 17377161315995 | M41: 18111796269189 | N41: 20311783916069
B42: Total Asset (Book Value) | C42: =SUM(C40:C41) -> 24514351948975 | D42: =SUM(D40:D41) -> 17377161315995 | E42: =SUM(E40:E41) -> 18111796269189 | F42: =SUM(F40:F41) -> 20311783916069 | H42: 300 | I42: NỢ PHẢI TRẢ | J42: Liabilities | K42: 13195700411669 | L42: 6210033388769 | M42: 6829845298714 | N42: 8878813931686
B43: Avg. of Total Asset (Book Value) | C43: - | D43: =AVERAGE(C42:D42) -> 20945756632485 | E43: =AVERAGE(D42:E42) -> 17744478792592 | F43: =AVERAGE(E42:F42) -> 19211790092629 | H43: 310 | I43: Nợ ngắn hạn | J43: Current Liabilities | K43: 13182047854402 | L43: 6195799689582 | M43: 6815609482547 | N43: 8864853420561
B44: Net Income | C44: =K85 -> 4375801849593 | D44: =L85 -> 48170557444 | E44: =M85 -> 248288982544 | F44: =N85 -> 528922307162 | H44: 311 | I44: Phải trả người bán ngắn hạn | J44: Accounts Payable | K44: 4283263896000 | L44: 1970635586928 | M44: 3330483232614 | N44: 2853606214481
B45: ROA | C45: - | D45: =D44/D43 -> 0.0022997764 | E45: =E44/E43 -> 0.013992464 | F45: =F44/F43 -> 0.027531131 | H45: 312 | I45: Người mua trả tiền trước ngắn hạn | J45: Advances from Customers | K45: 233052080172 | L45: 176845202295 | M45: 129957335766 | N45: 179998887975
H46: 313 | I46: Thuế và các khoản phải nộp Nhà nước | J46: Taxes and Other Payables to the State | K46: 309240420455 | L46: 5275868275 | M46: 145505586644 | N46: 74417109924
C47: 2021 | D47: 2022 | E47: 2023 | F47: 2024 | H47: 314 | I47: Phải trả người lao động | J47: Employee Payables | K47: 55566725013 | L47: 64245590725 | M47: 48600453107 | N47: 64468071697
B48: Total Revenue | C48: =K70 -> 86267008434432 | D48: =L70 -> 81189481215099 | E48: =M70 -> 52604763167190 | F48: =N70 -> 66712547798751 | H48: 315 | I48: Chi phí phải trả ngắn hạn | J48: Accrued Expenses | K48: 214800245166 | L48: 207561319455 | M48: 66684028030 | N48: 208807717032
B49: Avg. of Total Asset (Book Value) | C49: =C43 -> - | D49: =D43 -> 20945756632485 | E49: =E43 -> 17744478792592 | F49: =F43 -> 19211790092629 | H49: 319 | I49: Phải trả ngắn hạn khác | J49: Other Current Payables | K49: 3256582146203 | L49: 18979145366 | M49: 42122470287 | N49: 137451191503
B50: Total Asset Efficiency | C50: - | D50: =D48/D49 -> 3.876178 | E50: =E48/E49 -> 2.9645708 | F50: =F48/F49 -> 3.4724795 | H50: 320 | I50: Vay ngắn hạn | J50: Short-term Borrowings | K50: 4754513830764 | L50: 3545557150716 | M50: 2903786802438 | N50: 5310715159144
H51: 322 | I51: Quỹ khen thưởng, phúc lợi | J51: Bonus and Welfare Fund | K51: 75028510629 | L51: 206699825822 | M51: 148469573661 | N51: 35388068805
A52: 2. Operation Assets | H52: 330 | I52: Nợ dài hạn | J52: Non-current Liabilities | K52: 13652557267 | L52: 14233699187 | M52: 14235816167 | N52: 13960511125
A53: Short-term Assets' turnover | C53: 2021 | D53: 2022 | E53: 2023 | F53: 2024 | H53: 337 | I53: Phải trả dài hạn khác | J53: Other Long-term Payables | K53: 709500 | L53: 709500000 | M53: 709500000 | N53: 709500000
B54: Cost of Goods Sold | C54: =K71 -> 80500728426285 | D54: =L71 -> 77388423409761 | E54: =M71 -> 50476627454498 | F54: =N71 -> 63473799048283 | H54: 342 | I54: Dự phòng phải trả dài hạn | J54: Long-term Provisions | K54: 12943057267 | L54: 13524199187 | M54: 13526316167 | N54: 13251011125
B55: Operating Revenue | C55: =K70 -> 86267008434432 | D55: =L70 -> 81189481215099 | E55: =M70 -> 52604763167190 | F55: =N70 -> 66712547798751 | H55: 400 | I55: VỐN CHỦ SỞ HỮU | J55: Equity | K55: 11318651537306 | L55: 11167127927226 | M55: 11281950970475 | N55: 11432969984383
B56: Inventory | C56: =K14 -> 6384320637756 | D56: =L14 -> 3185372278891 | E56: =M14 -> 3749491109277 | F56: =N14 -> 3943145442782 | H56: 410 | I56: Vốn chủ sở hữu | J56: Owners' Equity | K56: 11318651537306 | L56: 11167127927226 | M56: 11281950970475 | N56: 11432969984383
B57: Avg. Inventory | C57: - | D57: =AVERAGE(C56:D56) -> 4.7848465e+12 | E57: =AVERAGE(D56:E56) -> 3467431694084 | F57: =AVERAGE(E56:F56) -> 3.8463183e+12 | H57: 411 | I57: Vốn góp của chủ sở hữu | J57: Contributed Capital | K57: 4934818960000 | L57: 5980549860000 | M57: 6159823090000 | N57: 6159823090000
B58: Accounts Receivable | C58: =SUM(K8,K22) -> 12077168369214 | D58: =SUM(L8,L22) -> 8556323027895 | E58: =SUM(M8,M22) -> 8546177472309 | F58: =SUM(N8,N22) -> 10789149284840 | H58: 411a | I58: Cổ phiếu phổ thông có quyền biểu quyết | J58: Ordinary Shares | K58: 4934818960000 | L58: 5980549860000 | M58: 6159823090000 | N58: 6159823090000
B59: Avg. Accounts Receivable | C59: - | D59: =AVERAGE(C58:D58) -> 1.0316746e+13 | E59: =AVERAGE(D58:E58) -> 8551250250102 | F59: =AVERAGE(E58:F58) -> 9.6676634e+12 | H59: 412 | I59: Thặng dư vốn cổ phần | J59: Share Premium | K59: 157292539068 | L59: 157292539068 | M59: 157292539068 | N59: 157292539068
B60: Inventory Turnover (times) | C60: - | D60: =D54/D57 -> 16.173648 | E60: =E54/E57 -> 14.557353 | F60: =F54/F57 -> 16.502482 | H60: 420 | I60: Quỹ khác thuộc vốn chủ sở hữu | J60: Other Equity Funds | K60: 90695201265 | L60: 187499009876 | M60: 77910496944 | N60: 50993213769
B61: Inventory Turnover Period (days) | C61: - | D61: =360/D60 -> 22.258429 | E61: =360/E60 -> 24.72977 | F61: =360/F60 -> 21.8149 | H61: 421 | I61: Lợi nhuận sau thuế chưa phân phối | J61: Retained Earnings | K61: 6135844836973 | L61: 4841786518282 | M61: 4886924844463 | N61: 5064861141546
B62: AR Turnover (times) | C62: - | D62: =D55/D59 -> 7.8696794 | E62: =E55/E59 -> 6.1517043 | F62: =F55/F59 -> 6.9005865 | H62: 421a | I62: LN chưa phân phối lũy kế năm trước | J62: Retained Earnings Brought Forward | K62: 1824320198455 | L62: 4793615960838 | M62: 4638635861919 | N62: 4576082907573
B63: AR Collection Period (day) | C63: - | D63: =360/D62 -> 45.745193 | E63: =360/E62 -> 58.520368 | F63: =360/F62 -> 52.169478 | H63: 421b | I63: LN chưa phân phối năm nay | J63: Current Year Retained Earnings | K63: 4311524638518 | L63: 48170557444 | M63: 248288982544 | N63: 488778233973
H64: 440 | I64: TỔNG NGUỒN VỐN | J64: Total Liabilities and Equity | K64: 24514351948975 | L64: 17377161315995 | M64: 18111796269189 | N64: 20311783916069
A65: Long-Term Operating Assets Efficiency | C65: 2021 | D65: 2022 | E65: 2023 | F65: 2024
B66: Fixed Asset | C66: =K25 -> 1134208705003 | D66: =L25 -> 1198450061079 | E66: =M25 -> 1016313002019 | F66: =N25 -> 844402354164 | H66: Mã số | I66: Chỉ tiêu | J66: Eng | K66: 2021 | L66: 30/9/2022 (VND) | M66: 30/9/2023 (VND) | N66: 30/9/2024 (VND)
B67: Avg. Fixed Asset | C67: - | D67: =AVERAGE(C66:D66) -> 1166329383041 | E67: =AVERAGE(D66:E66) -> 1107381531549 | F67: =AVERAGE(E66:F66) -> 9.3035768e+11 | H67: 1 | I67: Doanh thu bán hàng và cung cấp dịch vụ | J67: Revenue from sales and service provision | K67: 86441507897173 | L67: 81450228213277 | M67: 52881019564133 | N67: 67051370845971
B68: Averaged under-operation Fixed Asset | C68: =K32 -> 180277059193 | D68: =L32 -> 106037865309 | E68: =M32 -> 27180502737 | F68: =N32 -> 9027013569 | H68: 2 | I68: Các khoản giảm trừ doanh thu | J68: Sales deductions | K68: 174499462741 | L68: 260746998178 | M68: 276256396943 | N68: 338823047220
B69: Avg. under-operation Fixed Asset | C69: - | D69: =AVERAGE(C68:D68) -> 143157462251 | E69: =AVERAGE(D68:E68) -> 66609184023 | F69: =AVERAGE(E68:F68) -> 18103758153
B70: Fixed Asset Turnover (ORevenue / Avg Fixed Assets) | C70: - | D70: =D55/D67 -> 69.611108 | E70: =E55/E67 -> 47.503739 | F70: =F55/F67 -> 71.706344 | H70: 10 | I70: Doanh thu thuần về bán hàng và cung cấp dịch vụ | J70: Net revenue from sales and service provision | K70: 86267008434432 | L70: 81189481215099 | M70: 52604763167190 | N70: 66712547798751
B71: Fixed Asset Turnover (ORevenue / Avg under-operation Fixed Assets) | C71: - | D71: =D55/D69 -> 567.13412 | E71: =E55/E69 -> 789.7524 | F71: =F55/F69 -> 3685.011 | H71: 11 | I71: Giá vốn hàng bán và dịch vụ cung cấp | J71: Cost of goods sold and services provided | K71: 80500728426285 | L71: 77388423409761 | M71: 50476627454498 | N71: 63473799048283
H72: 20 | I72: Lợi nhuận gộp (20 = 10 - 11) | J72: Gross profit (20 = 10 - 11) | K72: 5766280008147 | L72: 3801057805338 | M72: 2128135712692 | N72: 3238748750468
A73: 3. Financial Assets | C73: 2021 | D73: 2022 | E73: 2023 | F73: 2024 | H73: 21 | I73: Doanh thu hoạt động tài chính | J73: Financial income | K73: 2660392557597 | L73: 425167604879 | M73: 800850256543 | N73: 652938094707
B74: Financial Revenue | C74: =K73 -> 2660392557597 | D74: =L73 -> 425167604879 | E74: =M73 -> 800850256543 | F74: =N73 -> 652938094707 | H74: 22 | I74: Chi phí tài chính | J74: Financial expenses | K74: 354050453366 | L74: 419889233636 | M74: 300217604297 | N74: 251550025718
B75: Financial Assets | C75: =SUM(K6,K34) -> 3249000000000 | D75: =SUM(L6,L34) -> 3398850000000 | E75: =SUM(M6,M34) -> 3610410958904 | F75: =SUM(N6,N34) -> 3616873825343 | H75: 25 | I75: Chi phí bán hàng | J75: Selling expenses | K75: 163982509811 | L75: 3469159524662 | M75: 2121829595199 | N75: 2858708812560
B76: Average Financial Assets | C76: - | D76: =AVERAGE(C75:D75) -> 3323925000000 | E76: =AVERAGE(D75:E75) -> 3504630479452 | F76: =AVERAGE(E75:F75) -> 3.6136424e+12 | H76: 26 | I76: Chi phí quản lý doanh nghiệp | J76: General and administrative expenses | K76: 2971926540542 | L76: 323017357209 | M76: 242553285595 | N76: 308367699972
B77: Financial assets' return | C77: - | D77: =D74/D76 -> 0.12791131 | E77: =E74/E76 -> 0.22851204 | F77: =F74/F76 -> 0.18068697 | H77: 30 | I77: Lợi nhuận thuần từ hoạt động kinh doanh | J77: Operating profit | K77: 253197996846 | L77: 14159294710 | M77: 264385484144 | N77: 473060306925
K78: 4847497574990
H79: 31 | I79: Thu nhập khác | J79: Other income | K79: 7884997850 | L79: 37281371157 | M79: 45338320487 | N79: 34684261898
H80: 32 | I80: Chi phí khác | J80: Other expenses | K80: 11164052377 | L80: 2028544004 | M80: 631991708 | N80: 5192249642
H81: 40 | I81: Lợi nhuận/(lỗ) khác (40 = 31 - 32) | J81: Other profit/(loss) (40 = 31 - 32) | K81: -3279054527 | L81: 35252827153 | M81: 44706328779 | N81: 29492012256
H82: 50 | I82: Tổng lợi nhuận kế toán trước thuế (50 = 30 + 40) | J82: Total accounting profit before tax (50 = 30 + 40) | K82: 4844218520463 | L82: 49412121863 | M82: 309091812923 | N82: 502552319181
H83: 51 | I83: Chi phí thuế TNDN hiện hành | J83: Current corporate income tax expense | K83: 515776476827 | L83: 23681645484 | M83: 1536979754 | N83: 99693200
H84: 52 | I84: Lợi ích thuế TNDN hoãn lại | J84: Deferred corporate income tax benefit | K84: -47359805957 | L84: -22440081065 | M84: 59265850625 | N84: 26469681181
H85: 60 | I85: Lợi nhuận thuần sau thuế TNDN (60 = 50 - 51 - 52) | J85: Net profit after corporate income tax (60 = 50 - 51 - 52) | K85: 4375801849593 | L85: 48170557444 | M85: 248288982544 | N85: 528922307162

Sheet 5. Profit Sharing
A1: 5.1.1. Profit Recovery and Retained Earnings Growth
J2: Income Statement
C3: 2022 | D3: 2023 | E3: 2024 | J3: Mã số | K3: Chỉ tiêu | L3: 2022 | M3: 2023 | N3: 2024
B4: Net Income | C4: =L22 -> 48170557444 | D4: =M22 -> 248288982544 | E4: =N22 -> 528922307162 | J4: 1 | K4: Revenue from sales and service provision | L4: 81450228213277 | M4: 52881019564133 | N4: 67051370845971
B5: Retained Earnings | C5: =L31 -> 4841786518282 | D5: =M31 -> 4886924844463 | E5: =N31 -> 5064861141546 | J5: 2 | K5: Sales deductions | L5: 260746998178 | M5: 276256396943 | N5: 338823047220
J7: 10 | K7: Net revenue from sales and service provision | L7: 81189481215099 | M7: 52604763167190 | N7: 66712547798751
A8: 5.1.2. Retention and Sustainable Growth | J8: 11 | K8: Cost of goods sold and services provided | L8: 77388423409761 | M8: 50476627454498 | N8: 63473799048283
J9: 20 | K9: Gross profit (20 = 10 - 11) | L9: 3801057805338 | M9: 2128135712692 | N9: 3238748750468
C10: 2023 | D10: 2024 | J10: 21 | K10: Financial income | L10: 425167604879 | M10: 800850256543 | N10: 652938094707
B11: Cash dividend per share | C11: 500 | D11: 500 | E11: (Source: HSG Annual Reports) | J11: 22 | K11: Financial expenses | L11: 419889233636 | M11: 300217604297 | N11: 251550025718
B12: Shares Outstanding | C12: 615982309 | D12: 620982309 | J12: 25 | K12: Selling expenses | L12: 3469159524662 | M12: 2121829595199 | N12: 2858708812560
B13: Dividend Payment | C13: =C11*C12 -> 307991154500 | D13: =D11*D12 -> 310491154500 | J13: 26 | K13: General and administrative expenses | L13: 323017357209 | M13: 242553285595 | N13: 308367699972
B14: Net Income | C14: =D4 -> 248288982544 | D14: =E4 -> 528922307162 | J14: 30 | K14: Operating profit | L14: 14159294710 | M14: 264385484144 | N14: 473060306925
B15: Payout Ratio | C15: =C13/C14 -> 1.2404544 | D15: =D13/D14 -> 0.58702602
J16: 31 | K16: Other income | L16: 37281371157 | M16: 45338320487 | N16: 34684261898
B17: Retention Ratio | C17: =1-C15 -> -0.24045437 | D17: =1-D15 -> 0.41297398 | J17: 32 | K17: Other expenses | L17: 2028544004 | M17: 631991708 | N17: 5192249642
J18: 40 | K18: Other profit/(loss) (40 = 31 - 32) | L18: 35252827153 | M18: 44706328779 | N18: 29492012256
C19: 2022 | D19: 2023 | E19: 2024 | J19: 50 | K19: Total accounting profit before tax (50 = 30 + 40) | L19: 49412121863 | M19: 309091812923 | N19: 502552319181
J20: 51 | K20: Current corporate income tax expense | L20: 23681645484 | M20: 1536979754 | N20: 99693200
B21: Net Income | C21: =C4 -> 48170557444 | D21: =D4 -> 248288982544 | E21: =E4 -> 528922307162 | J21: 52 | K21: Deferred corporate income tax benefit | L21: -22440081065 | M21: 59265850625 | N21: 26469681181
J22: 60 | K22: Net profit after corporate income tax (60 = 50 - 51 - 52) | L22: 48170557444 | M22: 248288982544 | N22: 528922307162
B23: Equity | C23: =L25 -> 11167127927226 | D23: =M25 -> 11281950970475 | E23: =N25 -> 11432969984383
B24: Average Equity | C24: — | D24: =(C23+D23)/2 -> 1.1224539e+13 | E24: =(D23+E23)/2 -> 11357460477429 | J24: Owner's Equity (Balance Sheet)
J25: 400 | K25: Equity | L25: 11167127927226 | M25: 11281950970475 | N25: 11432969984383
B26: ROE | C26: — | D26: =D21/D24 -> 0.022120193 | E26: =E21/E24 -> 0.046570473 | J26: 410 | K26: Owners' Equity | L26: 11167127927226 | M26: 11281950970475 | N26: 11432969984383
J27: 411 | K27: Contributed Capital | L27: 5980549860000 | M27: 6159823090000 | N27: 6159823090000
J28: 411a | K28: Ordinary Shares | L28: 5980549860000 | M28: 6159823090000 | N28: 6159823090000
C29: 2023 | D29: 2024 | J29: 412 | K29: Share Premium | L29: 157292539068 | M29: 157292539068 | N29: 157292539068
B30: Retention Ratio | C30: =C17 -> -0.24045437 | D30: =D17 -> 0.41297398 | J30: 420 | K30: Other Equity Funds | L30: 187499009876 | M30: 77910496944 | N30: 50993213769
B31: ROE | C31: =D26 -> 0.022120193 | D31: =E26 -> 0.046570473 | J31: 421 | K31: Retained Earnings | L31: 4841786518282 | M31: 4886924844463 | N31: 5064861141546
B32: g-equity | C32: =C30*C31 -> -0.0053188972 | D32: =D30*D31 -> 0.019232394 | J32: 421a | K32: Retained Earnings Brought Forward | L32: 4793615960838 | M32: 4638635861919 | N32: 4576082907573
J33: 421b | K33: Current Year Retained Earnings | L33: 48170557444 | M33: 248288982544 | N33: 488778233973
J34: 440 | K34: Total Liabilities and Equity | L34: 17377161315995 | M34: 18111796269189 | N34: 20311783916069
A35: 5.2. Dividend Policy Evolution
C37: Dividend Type | D37: Rate
B38: FY 2021-22 | C38: Share | D38: 0.03
B39: FY 2022-23 | C39: Cash | D39: 0.05
B40: FY 2023-24 | C40: Cash | D40: 0.05
B41: (Source: HSG Annual Reports)

Sheet 6. Overall assessment
B1: 2022 | C1: 2023 | D1: 2024 | H1: 0 | I1: 1 | J1: 1-0
A2: NI | B2: ='Income Statement'!E20 -> 48170557444 | C2: ='Income Statement'!F20 -> 248288982544 | D2: ='Income Statement'!G20 -> 528922307162 | H2: 2023 | I2: 2024 | J2: 24/23 | L2: ROA1 | M2: =SUM(M3:M5) -> 0.013538667 | N2: + | P2: Contribution (%) | S2: 2022 | T2: 2023 | U2: 2024
A3: Total assets | B3: ='Balance Sheet'!D42 -> 17377161315995 | C3: ='Balance Sheet'!E42 -> 18111796269189 | D3: ='Balance Sheet'!F42 -> 20311783916069 | G3: ROA | H3: =C2/((C3+B3)/2) -> 0.013992464 | I3: =D2/((D3+C3)/2) -> 0.027531131 | J3: =I3-H3 -> 0.013538667 | L3: Impact factor 1 | M3: =J5*H6*H7 -> 0.0095117741 | N3: + | O3: NI/SALE | P3: =ROUND(M3/M2*100,2) -> 70.26 | R3: Employee Cost / Revenue | S3: =ROUND(B11/B5*100,2) -> 1.26 | T3: =ROUND(C11/C5*100,2) -> 1.44 | U3: =ROUND(D11/D5*100,2) -> 1.48
A4: LT capital | B4: ='Balance Sheet'!D53+'Balance Sheet'!D57 -> 11181361626413 | C4: ='Balance Sheet'!E53+'Balance Sheet'!E57 -> 11296186786642 | D4: ='Balance Sheet'!F53+'Balance Sheet'!F57 -> 11446930495508 | G4: ROCE | H4: =C2/((C4+B4)/2) -> 0.022092176 | I4: =D2/((D4+C4)/2) -> 0.046512736 | J4: =I4-H4 -> 0.02442056 | L4: Impact factor 2 | M4: =I5*J6*H7 -> 0.0035831983 | N4: + | O4: Sale/ Ave Operating assets | P4: =ROUND(M4/M2*100,2) -> 26.47 | R4: Revenue / Employee | S4: =B5/B12 -> 1.4298958e+10 | T4: =C5/C12 -> 1.0126037e+10 | U4: =D5/D12 -> 1.2601539e+10
A5: Sale (Operation revenue) | B5: ='Income Statement'!E5 -> 81189481215099 | C5: ='Income Statement'!F5 -> 52604763167190 | D5: ='Income Statement'!G5 -> 66712547798751 | F5: 1 | G5: NI/SALE | H5: =C2/C5 -> 0.0047198955 | I5: =D2/D5 -> 0.0079283782 | J5: =I5-H5 -> 0.0032084827 | L5: Impact factor 3 | M5: =I5*I6*J7 -> 0.00044369436 | N5: + | O5: Ave Operating assets/Ave Total assets | P5: =ROUND(M5/M2*100,2) -> 3.28
A6: Operating assets | B6: =('Balance Sheet'!D3-'Balance Sheet'!D7-'Balance Sheet'!D18) + ('Balance Sheet'!D22-'Balance Sheet'!D35-'Balance Sheet'!D39) -> 13288998709765 | C6: =('Balance Sheet'!E3-'Balance Sheet'!E7-'Balance Sheet'!E18) + ('Balance Sheet'!E22-'Balance Sheet'!E35-'Balance Sheet'!E39) -> 13840549085908 | D6: =('Balance Sheet'!F3-'Balance Sheet'!F7-'Balance Sheet'!F18) + ('Balance Sheet'!F22-'Balance Sheet'!F35-'Balance Sheet'!F39) -> 16013502913296 | F6: 2 | G6: Sale/ Ave Operating assets | H6: =C5/((C6+B6)/2) -> 3.878042 | I6: =D5/((D6+C6)/2) -> 4.4692458 | J6: =I6-H6 -> 0.59120375
A7: Financial income | B7: ='Income Statement'!E8 -> 425167604879 | C7: ='Income Statement'!F8 -> 800850256543 | D7: ='Income Statement'!G8 -> 652938094707 | F7: 3 | G7: Ave Operating assets/Ave Total assets: | H7: =((C6+B6)/2)/((C3+B3)/2) -> 0.7644504 | I7: =((C6+D6)/2)/((C3+D3)/2) -> 0.77697216 | J7: =I7-H7 -> 0.012521758 | L7: ROA2 | M7: =SUM(M8:M10) -> 0.013538667 | N7: + | P7: Contribution (%)
A8: Financial assets | B8: ='Balance Sheet'!D35+'Balance Sheet'!D7 -> 3398850000000 | C8: ='Balance Sheet'!E7+'Balance Sheet'!E35 -> 3610410958904 | D8: ='Balance Sheet'!F35+'Balance Sheet'!F7 -> 3616873825343 | F8: 1 | G8: NI/Financial income | H8: =C2/C7 -> 0.31003172 | I8: =D2/D7 -> 0.81006501 | J8: =I8-H8 -> 0.50003329 | L8: Impact factor 1 | M8: =J8*H9*H10 -> 0.022567684 | N8: + | O8: NI/Financial income | P8: =ROUND(M8/M7*100,2) -> 166.69
A9: LT assets | B9: ='Balance Sheet'!D22 -> 5118727087531 | C9: ='Balance Sheet'!E22 -> 4924991584484 | D9: ='Balance Sheet'!F22 -> 4763897298254 | F9: 2 | G9: Financial income/ Ave financial assets | H9: =C7/((C8+B8)/2) -> 0.22851204 | I9: =D7/((D8+C8)/2) -> 0.18068697 | J9: =I9-H9 -> -0.047825069 | L9: Impact factor 2 | M9: =I8*J9*H10 -> -0.0076516389 | N9: - | O9: Financial income/ Ave financial assets | P9: =ROUND(M9/M7*100,2) -> -56.52
A10: OE | B10: ='Balance Sheet'!D57 -> 11167127927226 | C10: ='Balance Sheet'!E57 -> 11281950970475 | D10: ='Balance Sheet'!F57 -> 11432969984383 | F10: 3 | G10: Ave Financial assets/Ave Total assets | H10: =((C8+B8)/2)/((C3+B3)/2) -> 0.19750541 | I10: =((D8+C8)/2)/((D3+C3)/2) -> 0.18809504 | J10: =I10-H10 -> -0.0094103673 | L10: Impact factor 3 | M10: =I8*I9*J10 -> -0.0013773785 | N10: - | O10: Ave Financial assets/Ave Total assets | P10: =ROUND(M10/M7*100,2) -> -10.17
A11: Employee Cost | B11: 1020188374598 | C11: 756748227290 | D11: 984900095440 | E11: Notes of FSs mục 32 hoặc 33 (tùy năm) | F11: 2 | G11: Sale/ Ave Long term assets | H11: =C5/((C9+B9)/2) -> 10.475157 | I11: =D5/((D9+C9)/2) -> 13.770939 | J11: =I11-H11 -> 3.2957821
A12: Number of Employees | B12: 5678 | C12: 5195 | D12: 5294 | E12: Notes of FSs mục 1 | F12: 3 | G12: Ave Longterm assets/ Ave Long term Capital employed | H12: =((C9+B9)/2)/((C4+B4)/2) -> 0.44683337 | I12: =((D9+C9)/2)/((D4+C4)/2) -> 0.42601411 | J12: =I12-H12 -> -0.020819258 | L12: ROCE | M12: =SUM(M13:M15) -> 0.02442056 | N12: + | P12: Contribution (%)
A13: Hoa Phat Group | H13: 0 | I13: 1 | J13: 1-0 | L13: Impact factor 1 | M13: =J5*H11*H12 -> 0.015017783 | N13: + | O13: NI/SALE | P13: =ROUND(M13/M12*100,2) -> 61.5
A14: Fiscal Year | B14: FY 2024 | C14: FY 2023 | D14: FY 2022 | H14: 2023 | I14: 2024 | J14: 24/23 | L14: Impact factor 2 | M14: =I5*J11*H12 -> 0.011675848 | N14: + | O14: Sale/ Ave Long term assets | P14: =ROUND(M14/M12*100,2) -> 47.81
A15: Return on Equity (ROE) | B15: 0.1105 | C15: 0.0684 | D15: 0.0904 | G15: ROE | H15: =C2/((C10+B10)/2) -> 0.022120193 | I15: =D2/((D10+C10)/2) -> 0.046570473 | J15: =I15-H15 -> 0.02445028 | L15: Impact factor 3 | M15: =I5*I11*J12 -> -0.0022730718 | N15: - | O15: Ave Longterm assets/ Ave Long term Capital employed | P15: =ROUND(M15/M12*100,2) -> -9.31
A16: Return on Assets (ROA) | B16: 0.0443 | C16: 0.0338 | D16: 0.0469 | F16: 1 | G16: NI/SALE | H16: =C2/C5 -> 0.0047198955 | I16: =D2/D5 -> 0.0079283782 | J16: =I16-H16 -> 0.0032084827
A17: Return on Capital Employed (ROCE) | B17: 0.098 | C17: 0.083 | D17: 0.121 | F17: 2 | G17: SALE/AVE TOTAL ASSET | H17: =C5/((C3+B3)/2) -> 2.9645708 | I17: =D5/((D3+C3)/2) -> 3.4724795 | J17: =I17-H17 -> 0.50790876 | L17: ROE | M17: =SUM(M18:M20) -> 0.02445028 | N17: + | P17: Contribution (%)
A18: Nam Kim | F18: 3 | G18: AVE TOTAL CAPITAL/ AVE OE | H18: =((C3+B3)/2)/((C10+B10)/2) -> 1.5808648 | I18: =((D3+C3)/2)/((D10+C10)/2) -> 1.6915569 | J18: =I18-H18 -> 0.1106921 | L18: Impact factor 1 | M18: =J16*H17*H18 -> 0.015036828 | N18: + | O18: NI/SALE | P18: =ROUND(M18/M17*100,2) -> 61.5
A19: Fiscal Year | B19: FY 2024 | C19: FY 2023 | D19: FY 2022 | L19: Impact factor 2 | M19: =I16*J17*H18 -> 0.0063659727 | N19: + | O19: Sale/Ave Total assets | P19: =ROUND(M19/M17*100,2) -> 26.04
A20: Return on Equity (ROE) | B20: 0.0802 | C20: 0.0219 | D20: -0.0226 | L20: Impact factor 3 | M20: =I16*I17*J18 -> 0.0030474786 | N20: + | O20: Ave Total Captital/Ave OE | P20: =ROUND(M20/M17*100,2) -> 12.46
A21: Return on Assets (ROA) | B21: 0.0337 | C21: 0.0181 | D21: 0.004
A22: Return on Capital Employed (ROCE) | B22: 0.118 | C22: 0.068 | D22: 0.017
